{
  "source": {
    "name": "抖音热榜",
    "description": "抖音热门话题",
    "url": "https://60s.viki.moe/v2/douyin",
    "lastUpdate": "2026-07-09T01:53:41.586Z"
  },
  "data": [
    {
      "title": "从空间站俯瞰台风巴威有多大",
      "hot_value": 12105893,
      "cover": "https://p26-sign.douyinpic.com/tos-cn-p-0015/oIJi604AiNQ3aqpIlRP9FgBAzIPI3ka4WTYPj~noop.jpeg?lk3s=bfd515bb&x-expires=1783580400&x-signature=WpeUt1OBiVZUWxB7PyHld%2B35I1Q%3D&from=3218412987",
      "link": "https://www.douyin.com/search/%E4%BB%8E%E7%A9%BA%E9%97%B4%E7%AB%99%E4%BF%AF%E7%9E%B0%E5%8F%B0%E9%A3%8E%E5%B7%B4%E5%A8%81%E6%9C%89%E5%A4%9A%E5%A4%A7",
      "event_time": "2026/07/08 18:18:13",
      "event_time_at": 1783505893,
      "active_time": "2026-07-09 09:53:19",
      "active_time_at": 1783590799000
    },
    {
      "title": "95后女孩工位安在南极深海",
      "hot_value": 11775050,
      "cover": "https://p3-sign.douyinpic.com/tos-cn-p-0015/o81JIMXAABiVTgCBm9cBfixzoANtCIXPenJsuQ~noop.jpeg?lk3s=bfd515bb&x-expires=1783580400&x-signature=YPBKrgMYa0pjGR8FvbT8uTkQ8Y0%3D&from=3218412987",
      "link": "https://www.douyin.com/search/95%E5%90%8E%E5%A5%B3%E5%AD%A9%E5%B7%A5%E4%BD%8D%E5%AE%89%E5%9C%A8%E5%8D%97%E6%9E%81%E6%B7%B1%E6%B5%B7",
      "event_time": "2026/07/08 19:59:40",
      "event_time_at": 1783511980,
      "active_time": "2026-07-09 09:53:19",
      "active_time_at": 1783590799000
    },
    {
      "title": "我国人工智能产业加速发展壮大",
      "hot_value": 11301100,
      "cover": "https://p3-sign.douyinpic.com/tos-cn-p-0015/o4PGIBiCG4NYcHLNADBAIpJyeV1g9BlAoviyfj~noop.jpeg?lk3s=bfd515bb&x-expires=1783580400&x-signature=2sFg50MElBpEjQ7O%2BS1xD3jOJqQ%3D&from=3218412987",
      "link": "https://www.douyin.com/search/%E6%88%91%E5%9B%BD%E4%BA%BA%E5%B7%A5%E6%99%BA%E8%83%BD%E4%BA%A7%E4%B8%9A%E5%8A%A0%E9%80%9F%E5%8F%91%E5%B1%95%E5%A3%AE%E5%A4%A7",
      "event_time": "2026/07/08 20:55:32",
      "event_time_at": 1783515332,
      "active_time": "2026-07-09 09:53:19",
      "active_time_at": 1783590799000
    },
    {
      "title": "直击广西水情",
      "hot_value": 11281479,
      "cover": "https://p3-sign.douyinpic.com/obj/webcast-cover/7660000033678052147?lk3s=bfd515bb&x-expires=1783580400&x-signature=6UGcCwJfadED5zP0rqW8JIvEvfY%3D&from=3218412987",
      "link": "https://www.douyin.com/search/%E7%9B%B4%E5%87%BB%E5%B9%BF%E8%A5%BF%E6%B0%B4%E6%83%85",
      "event_time": "2026/07/08 21:33:11",
      "event_time_at": 1783517591,
      "active_time": "2026-07-09 09:53:19",
      "active_time_at": 1783590799000
    },
    {
      "title": "四川高县4.8级地震",
      "hot_value": 10507096,
      "cover": "https://p3-sign.douyinpic.com/tos-cn-p-0015/oYC97Tip3ZXQKODMAGSf5dgIBfAkiACrNBSquI~noop.jpeg?lk3s=bfd515bb&x-expires=1783580400&x-signature=IuI0lBvtCN1OqsBAEBGvqSW%2FRVE%3D&from=3218412987",
      "link": "https://www.douyin.com/search/%E5%9B%9B%E5%B7%9D%E9%AB%98%E5%8E%BF4.8%E7%BA%A7%E5%9C%B0%E9%9C%87",
      "event_time": "2026/07/09 07:52:44",
      "event_time_at": 1783554764,
      "active_time": "2026-07-09 09:53:19",
      "active_time_at": 1783590799000
    },
    {
      "title": "当机甲平台驶入洪水校园",
      "hot_value": 10277147,
      "cover": "https://p3-sign.douyinpic.com/tos-cn-p-0015/owEfgqnBfABnBPDsAllOIGIgWF9AoTqzyNEIAz~noop.jpeg?lk3s=bfd515bb&x-expires=1783580400&x-signature=Xk3uLM3cx0CNfRWvmVuZw2lbmDw%3D&from=3218412987",
      "link": "https://www.douyin.com/search/%E5%BD%93%E6%9C%BA%E7%94%B2%E5%B9%B3%E5%8F%B0%E9%A9%B6%E5%85%A5%E6%B4%AA%E6%B0%B4%E6%A0%A1%E5%9B%AD",
      "event_time": "2026/07/09 08:25:33",
      "event_time_at": 1783556733,
      "active_time": "2026-07-09 09:53:19",
      "active_time_at": 1783590799000
    },
    {
      "title": "17级台风威力有多大",
      "hot_value": 9182492,
      "cover": "https://p3-sign.douyinpic.com/tos-cn-p-0015/oUhIwyaPNNZmRiiPQCrEk6NBig9EPXI6MIAA3~noop.jpeg?lk3s=bfd515bb&x-expires=1783580400&x-signature=51K8ERLev7Uj%2FuL4RqFxuijFVwE%3D&from=3218412987",
      "link": "https://www.douyin.com/search/17%E7%BA%A7%E5%8F%B0%E9%A3%8E%E5%A8%81%E5%8A%9B%E6%9C%89%E5%A4%9A%E5%A4%A7",
      "event_time": "2026/07/08 11:25:37",
      "event_time_at": 1783481137,
      "active_time": "2026-07-09 09:53:19",
      "active_time_at": 1783590799000
    },
    {
      "title": "直击洪水过境后的云表镇",
      "hot_value": 9119237,
      "cover": "https://p26-sign.douyinpic.com/tos-cn-p-0015/oEI66uQiPzIamOgFEQFPIrBHAibxIAO7szika~noop.jpeg?lk3s=bfd515bb&x-expires=1783580400&x-signature=j%2FZTPWnP%2Ba%2FL1CcaT1VsVXwRipg%3D&from=3218412987",
      "link": "https://www.douyin.com/search/%E7%9B%B4%E5%87%BB%E6%B4%AA%E6%B0%B4%E8%BF%87%E5%A2%83%E5%90%8E%E7%9A%84%E4%BA%91%E8%A1%A8%E9%95%87",
      "event_time": "2026/07/09 08:11:51",
      "event_time_at": 1783555911,
      "active_time": "2026-07-09 09:53:19",
      "active_time_at": 1783590799000
    },
    {
      "title": "万物皆可波点风",
      "hot_value": 9111223,
      "cover": "https://p26-sign.douyinpic.com/tos-cn-p-0015c000-ce/oUXAbpFTMIDz7gEAGy3wffEOqMIU9x1EoFEN1B~noop.jpeg?lk3s=bfd515bb&x-expires=1783580400&x-signature=zkLaWf2whxMRF846gSkgqnDuh2Y%3D&from=3218412987",
      "link": "https://www.douyin.com/search/%E4%B8%87%E7%89%A9%E7%9A%86%E5%8F%AF%E6%B3%A2%E7%82%B9%E9%A3%8E",
      "event_time": "2026/07/08 10:41:34",
      "event_time_at": 1783478494,
      "active_time": "2026-07-09 09:53:19",
      "active_time_at": 1783590799000
    },
    {
      "title": "广西部分地区今日仍有大到暴雨",
      "hot_value": 8909449,
      "cover": "https://p11-sign.douyinpic.com/tos-cn-p-0015/ocfYBxeGagkL73UBw024KnYddCSAlIEeLJUhgA~noop.jpeg?lk3s=bfd515bb&x-expires=1783580400&x-signature=rIZEcJiuugV43Y2alaIzcnFVBbQ%3D&from=3218412987",
      "link": "https://www.douyin.com/search/%E5%B9%BF%E8%A5%BF%E9%83%A8%E5%88%86%E5%9C%B0%E5%8C%BA%E4%BB%8A%E6%97%A5%E4%BB%8D%E6%9C%89%E5%A4%A7%E5%88%B0%E6%9A%B4%E9%9B%A8",
      "event_time": "2026/07/09 08:21:19",
      "event_time_at": 1783556479,
      "active_time": "2026-07-09 09:53:19",
      "active_time_at": 1783590799000
    },
    {
      "title": "中国U17男足不敌坦桑尼亚",
      "hot_value": 8876533,
      "cover": "https://p26-sign.douyinpic.com/tos-cn-p-0015/oYbflFKvAyX91Dn8IKUA1oUfl5EATqPNgIBOIz~noop.jpeg?lk3s=bfd515bb&x-expires=1783580400&x-signature=FfPMdk2MxlnGMPpQpmh4zM6Wp68%3D&from=3218412987",
      "link": "https://www.douyin.com/search/%E4%B8%AD%E5%9B%BDU17%E7%94%B7%E8%B6%B3%E4%B8%8D%E6%95%8C%E5%9D%A6%E6%A1%91%E5%B0%BC%E4%BA%9A",
      "event_time": "2026/07/08 21:47:24",
      "event_time_at": 1783518444,
      "active_time": "2026-07-09 09:53:19",
      "active_time_at": 1783590799000
    },
    {
      "title": "凡人修仙传大晋实力有多强",
      "hot_value": 8835602,
      "cover": "https://p3-sign.douyinpic.com/tos-cn-p-0015/ogBsiDQAE0AL2IWsVU7ReleowbGZBCfQkH7UyK~noop.jpeg?lk3s=bfd515bb&x-expires=1783580400&x-signature=VsOPPuPabX6k7RQ5FqtKzXjmI2g%3D&from=3218412987",
      "link": "https://www.douyin.com/search/%E5%87%A1%E4%BA%BA%E4%BF%AE%E4%BB%99%E4%BC%A0%E5%A4%A7%E6%99%8B%E5%AE%9E%E5%8A%9B%E6%9C%89%E5%A4%9A%E5%BC%BA",
      "event_time": "2026/07/08 15:56:56",
      "event_time_at": 1783497416,
      "active_time": "2026-07-09 09:53:19",
      "active_time_at": 1783590799000
    },
    {
      "title": "埃及总统发声",
      "hot_value": 8412034,
      "cover": "https://p11-sign.douyinpic.com/tos-cn-p-0015/og6p6AfhamIAe771BiAEISFEYUzaXUNqDoBeCI~noop.jpeg?lk3s=bfd515bb&x-expires=1783580400&x-signature=h6oeV%2BpbhxQvYWLKuQPGch6gcH0%3D&from=3218412987",
      "link": "https://www.douyin.com/search/%E5%9F%83%E5%8F%8A%E6%80%BB%E7%BB%9F%E5%8F%91%E5%A3%B0",
      "event_time": "2026/07/08 14:52:31",
      "event_time_at": 1783493551,
      "active_time": "2026-07-09 09:53:19",
      "active_time_at": 1783590799000
    },
    {
      "title": "广西百色辟谣网传严重洪灾视频",
      "hot_value": 8410627,
      "cover": "https://p11-sign.douyinpic.com/tos-cn-i-dy/81544baf00494729a78ee621c1fd13da~noop.jpeg?lk3s=bfd515bb&x-expires=1783580400&x-signature=xPbVhGO%2BRSaIHjJiFsTwm5pS1kA%3D&from=3218412987",
      "link": "https://www.douyin.com/search/%E5%B9%BF%E8%A5%BF%E7%99%BE%E8%89%B2%E8%BE%9F%E8%B0%A3%E7%BD%91%E4%BC%A0%E4%B8%A5%E9%87%8D%E6%B4%AA%E7%81%BE%E8%A7%86%E9%A2%91",
      "event_time": "2026/07/08 20:18:41",
      "event_time_at": 1783513121,
      "active_time": "2026-07-09 09:53:19",
      "active_time_at": 1783590799000
    },
    {
      "title": "各行各业版主打歌群像运镜",
      "hot_value": 8267579,
      "cover": "https://p11-sign.douyinpic.com/tos-cn-p-0015/oIqyHDiQydFHAIRfAgiYqCqXe69BTADOEQWBII~noop.jpeg?lk3s=bfd515bb&x-expires=1783580400&x-signature=%2B7sSolaFs72aACNYXkI1KVBPobc%3D&from=3218412987",
      "link": "https://www.douyin.com/search/%E5%90%84%E8%A1%8C%E5%90%84%E4%B8%9A%E7%89%88%E4%B8%BB%E6%89%93%E6%AD%8C%E7%BE%A4%E5%83%8F%E8%BF%90%E9%95%9C",
      "event_time": "2026/07/08 21:35:46",
      "event_time_at": 1783517746,
      "active_time": "2026-07-09 09:53:19",
      "active_time_at": 1783590799000
    },
    {
      "title": "法国vs摩洛哥前瞻",
      "hot_value": 7911887,
      "cover": "https://p11-sign.douyinpic.com/tos-cn-p-0015/oI0OYhTiKseQFIHIoBi1A6BBgRDVGA0jf3JAQ9~noop.jpeg?lk3s=bfd515bb&x-expires=1783580400&x-signature=%2Bu9S4AFHX%2FgVKJCCx5lRdzofB4g%3D&from=3218412987",
      "link": "https://www.douyin.com/search/%E6%B3%95%E5%9B%BDvs%E6%91%A9%E6%B4%9B%E5%93%A5%E5%89%8D%E7%9E%BB",
      "event_time": "2026/07/09 08:30:33",
      "event_time_at": 1783557033,
      "active_time": "2026-07-09 09:53:19",
      "active_time_at": 1783590799000
    },
    {
      "title": "广西贵港上万名师生被困",
      "hot_value": 7850431,
      "cover": "https://p3-sign.douyinpic.com/tos-cn-p-0015/o8SlAnfDDQsx93qA0mdixTvJMBgALEnfFMA8Qg~noop.jpeg?lk3s=bfd515bb&x-expires=1783580400&x-signature=6vqht1RSlX61ZdcqMiZT5YIrKVY%3D&from=3218412987",
      "link": "https://www.douyin.com/search/%E5%B9%BF%E8%A5%BF%E8%B4%B5%E6%B8%AF%E4%B8%8A%E4%B8%87%E5%90%8D%E5%B8%88%E7%94%9F%E8%A2%AB%E5%9B%B0",
      "event_time": "2026/07/08 18:32:04",
      "event_time_at": 1783506724,
      "active_time": "2026-07-09 09:53:19",
      "active_time_at": 1783590799000
    },
    {
      "title": "当阿根廷球迷上了埃及司机的车",
      "hot_value": 7783499,
      "cover": "https://p26-sign.douyinpic.com/tos-cn-p-0015/o4qBc7GDLmTBmhaxe7eAAC9BvOCQgGBeAUosrI~noop.jpeg?lk3s=bfd515bb&x-expires=1783580400&x-signature=V54OllQzrK73t%2BuJAQhj2%2FWnCmY%3D&from=3218412987",
      "link": "https://www.douyin.com/search/%E5%BD%93%E9%98%BF%E6%A0%B9%E5%BB%B7%E7%90%83%E8%BF%B7%E4%B8%8A%E4%BA%86%E5%9F%83%E5%8F%8A%E5%8F%B8%E6%9C%BA%E7%9A%84%E8%BD%A6",
      "event_time": "2026/07/08 19:58:25",
      "event_time_at": 1783511905,
      "active_time": "2026-07-09 09:53:19",
      "active_time_at": 1783590799000
    },
    {
      "title": "抖音网友善意正送往广西灾区",
      "hot_value": 7772162,
      "cover": "https://p3-sign.douyinpic.com/tos-cn-p-0015/ocyIiyYxgEMBGQmCcZJGeB07pnALTMcAfofUgm~noop.jpeg?lk3s=bfd515bb&x-expires=1783580400&x-signature=Sjs%2Fw0%2Byjlxcd0WkxJsKA0pivsM%3D&from=3218412987",
      "link": "https://www.douyin.com/search/%E6%8A%96%E9%9F%B3%E7%BD%91%E5%8F%8B%E5%96%84%E6%84%8F%E6%AD%A3%E9%80%81%E5%BE%80%E5%B9%BF%E8%A5%BF%E7%81%BE%E5%8C%BA",
      "event_time": "2026/07/08 18:55:42",
      "event_time_at": 1783508142,
      "active_time": "2026-07-09 09:53:19",
      "active_time_at": 1783590799000
    },
    {
      "title": "湖北一家三口被大风卷走坠楼身亡",
      "hot_value": 7768613,
      "cover": "https://p26-sign.douyinpic.com/tos-cn-p-0015/o84QDgMAOIIaZcHitPNBORAPiaK1AkyyINIx0~noop.jpeg?lk3s=bfd515bb&x-expires=1783580400&x-signature=b9IkyRVXAjo%2F70SJIXrQJzJm74s%3D&from=3218412987",
      "link": "https://www.douyin.com/search/%E6%B9%96%E5%8C%97%E4%B8%80%E5%AE%B6%E4%B8%89%E5%8F%A3%E8%A2%AB%E5%A4%A7%E9%A3%8E%E5%8D%B7%E8%B5%B0%E5%9D%A0%E6%A5%BC%E8%BA%AB%E4%BA%A1",
      "event_time": "2026/07/08 16:04:49",
      "event_time_at": 1783497889,
      "active_time": "2026-07-09 09:53:19",
      "active_time_at": 1783590799000
    },
    {
      "title": "功夫女足发声明抵制倒卖门票",
      "hot_value": 7759679,
      "cover": "https://p5-ex-gddgtc-sign.douyinpic.com/tos-cn-p-0015/owoqXhB1gAveB9T8gIFiTADDAfskNEgEAABVOI~noop.jpeg?lk3s=bfd515bb&x-expires=1783580400&x-signature=09DIofVxMfJq3vRdoM3hPIVXc2I%3D&from=3218412987",
      "link": "https://www.douyin.com/search/%E5%8A%9F%E5%A4%AB%E5%A5%B3%E8%B6%B3%E5%8F%91%E5%A3%B0%E6%98%8E%E6%8A%B5%E5%88%B6%E5%80%92%E5%8D%96%E9%97%A8%E7%A5%A8",
      "event_time": "2026/07/08 15:53:47",
      "event_time_at": 1783497227,
      "active_time": "2026-07-09 09:53:19",
      "active_time_at": 1783590799000
    },
    {
      "title": "和我吃饭从不A钱之人",
      "hot_value": 7759154,
      "cover": "https://p26-sign.douyinpic.com/tos-cn-i-0813c000-ce/ogPiPAacCLyAMLXsOsEAhUvkAAMKi8BBnwnyI~noop.jpeg?lk3s=bfd515bb&x-expires=1783580400&x-signature=cmmYEd5F5fJZSunwuUm%2F2aegn2w%3D&from=3218412987",
      "link": "https://www.douyin.com/search/%E5%92%8C%E6%88%91%E5%90%83%E9%A5%AD%E4%BB%8E%E4%B8%8DA%E9%92%B1%E4%B9%8B%E4%BA%BA",
      "event_time": "2026/07/08 14:33:01",
      "event_time_at": 1783492381,
      "active_time": "2026-07-09 09:53:19",
      "active_time_at": 1783590799000
    },
    {
      "title": "慢充旅行太治愈了",
      "hot_value": 7747104,
      "cover": "https://p11-sign.douyinpic.com/tos-cn-p-0015/oQVegfAiTe9ffgAlJABdQBFhACiY3qFAefqphse~noop.jpeg?lk3s=bfd515bb&x-expires=1783580400&x-signature=tcfJTsCMK2MjnduFcm3H9VLg2Kw%3D&from=3218412987",
      "link": "https://www.douyin.com/search/%E6%85%A2%E5%85%85%E6%97%85%E8%A1%8C%E5%A4%AA%E6%B2%BB%E6%84%88%E4%BA%86",
      "event_time": "2026/07/08 13:47:03",
      "event_time_at": 1783489623,
      "active_time": "2026-07-09 09:53:19",
      "active_time_at": 1783590799000
    },
    {
      "title": "哈兰德名场面评选大会",
      "hot_value": 7740247,
      "cover": "https://p11-sign.douyinpic.com/tos-cn-p-0015/oMe9HAXxAUIQbBJ1OsC9s7FJIBjqgeENzg4oAQ~noop.jpeg?lk3s=bfd515bb&x-expires=1783580400&x-signature=SRxSfRwm%2Bj4g8vncNHl%2FZzXMDJ4%3D&from=3218412987",
      "link": "https://www.douyin.com/search/%E5%93%88%E5%85%B0%E5%BE%B7%E5%90%8D%E5%9C%BA%E9%9D%A2%E8%AF%84%E9%80%89%E5%A4%A7%E4%BC%9A",
      "event_time": "2026/07/08 19:03:33",
      "event_time_at": 1783508613,
      "active_time": "2026-07-09 09:53:19",
      "active_time_at": 1783590799000
    },
    {
      "title": "徐明浩这个舞我能跳",
      "hot_value": 7737931,
      "cover": "https://p26-sign.douyinpic.com/tos-cn-p-0015/oY5YE2iPyWC0BU3NAABAIhJweT1g0BRAluiaf3~noop.jpeg?lk3s=bfd515bb&x-expires=1783580400&x-signature=%2BLygo0wu5oVxd4m3s2YH1a08r5g%3D&from=3218412987",
      "link": "https://www.douyin.com/search/%E5%BE%90%E6%98%8E%E6%B5%A9%E8%BF%99%E4%B8%AA%E8%88%9E%E6%88%91%E8%83%BD%E8%B7%B3",
      "event_time": "2026/07/08 19:01:28",
      "event_time_at": 1783508488,
      "active_time": "2026-07-09 09:53:19",
      "active_time_at": 1783590799000
    },
    {
      "title": "骁唤醒了我的江湖病",
      "hot_value": 7729511,
      "cover": "https://p11-sign.douyinpic.com/tos-cn-p-0015/o8hEelj5IGhADoRBBHnDfAj9cRAFCT5gMy3qIP~noop.jpeg?lk3s=bfd515bb&x-expires=1783580400&x-signature=Kkb5LAVI368z0drzlANwEDzj3%2BM%3D&from=3218412987",
      "link": "https://www.douyin.com/search/%E9%AA%81%E5%94%A4%E9%86%92%E4%BA%86%E6%88%91%E7%9A%84%E6%B1%9F%E6%B9%96%E7%97%85",
      "event_time": "2026/07/08 12:36:52",
      "event_time_at": 1783485412,
      "active_time": "2026-07-09 09:53:19",
      "active_time_at": 1783590799000
    },
    {
      "title": "OMG你香到我啦",
      "hot_value": 7726137,
      "cover": "https://p3-sign.douyinpic.com/tos-cn-p-0015/oIEcGO9AQAAfjQBLIqegTyzbCBFzITSD0SdDFy~noop.jpeg?lk3s=bfd515bb&x-expires=1783580400&x-signature=MBE5vJtPV3eIzXxQ%2B7xvBXJWcXM%3D&from=3218412987",
      "link": "https://www.douyin.com/search/OMG%E4%BD%A0%E9%A6%99%E5%88%B0%E6%88%91%E5%95%A6",
      "event_time": "2026/07/08 11:14:57",
      "event_time_at": 1783480497,
      "active_time": "2026-07-09 09:53:19",
      "active_time_at": 1783590799000
    },
    {
      "title": "用特效回到2018年的夏天",
      "hot_value": 7715038,
      "cover": "https://p11-sign.douyinpic.com/tos-cn-p-0015c000-ce/ooQGe06qIysBQwLgUemAVT0ed7s7DJBlXIJPZz~noop.jpeg?lk3s=bfd515bb&x-expires=1783580400&x-signature=gwoErp%2FtQsVnYtGU5TRfhh4Ymr8%3D&from=3218412987",
      "link": "https://www.douyin.com/search/%E7%94%A8%E7%89%B9%E6%95%88%E5%9B%9E%E5%88%B02018%E5%B9%B4%E7%9A%84%E5%A4%8F%E5%A4%A9",
      "event_time": "2026/07/08 14:41:45",
      "event_time_at": 1783492905,
      "active_time": "2026-07-09 09:53:19",
      "active_time_at": 1783590799000
    },
    {
      "title": "密室四怂组队能吵吵绝不动腿",
      "hot_value": 7704701,
      "cover": "https://p11-sign.douyinpic.com/tos-cn-p-0015/oYz5UBIq5DDfAIAfISNBClDNEEF27mZEJcSufr~noop.jpeg?lk3s=bfd515bb&x-expires=1783580400&x-signature=RqHQIszi49ojyEwH65Fb9cQ5OBk%3D&from=3218412987",
      "link": "https://www.douyin.com/search/%E5%AF%86%E5%AE%A4%E5%9B%9B%E6%80%82%E7%BB%84%E9%98%9F%E8%83%BD%E5%90%B5%E5%90%B5%E7%BB%9D%E4%B8%8D%E5%8A%A8%E8%85%BF",
      "event_time": "2026/07/08 14:34:26",
      "event_time_at": 1783492466,
      "active_time": "2026-07-09 09:53:19",
      "active_time_at": 1783590799000
    },
    {
      "title": "无限流鼻祖恐怖游轮定档",
      "hot_value": 7696546,
      "cover": "https://p3-sign.douyinpic.com/tos-cn-p-0015/oAfhNdbAABBiuTgE3JBSCqI0TEZewr9qaijABt~noop.jpeg?lk3s=bfd515bb&x-expires=1783580400&x-signature=27iB%2B5ScctFujdJnm8%2BXtNlRfMk%3D&from=3218412987",
      "link": "https://www.douyin.com/search/%E6%97%A0%E9%99%90%E6%B5%81%E9%BC%BB%E7%A5%96%E6%81%90%E6%80%96%E6%B8%B8%E8%BD%AE%E5%AE%9A%E6%A1%A3",
      "event_time": "2026/07/08 14:16:53",
      "event_time_at": 1783491413,
      "active_time": "2026-07-09 09:53:19",
      "active_time_at": 1783590799000
    },
    {
      "title": "我的大学生三下乡日记",
      "hot_value": 7688336,
      "cover": "https://p26-sign.douyinpic.com/tos-cn-i-0813c000-ce/oU7PJgfD8EuT7MUBfv8uBkiXIEpAOE0AFAAeIg~noop.jpeg?lk3s=bfd515bb&x-expires=1783580400&x-signature=tukCNL8bC4m%2F3%2BzVZGm9gn05m24%3D&from=3218412987",
      "link": "https://www.douyin.com/search/%E6%88%91%E7%9A%84%E5%A4%A7%E5%AD%A6%E7%94%9F%E4%B8%89%E4%B8%8B%E4%B9%A1%E6%97%A5%E8%AE%B0",
      "event_time": "2026/07/08 10:25:58",
      "event_time_at": 1783477558,
      "active_time": "2026-07-09 09:53:19",
      "active_time_at": 1783590799000
    },
    {
      "title": "管泽元再现姆巴佩之剑吟唱",
      "hot_value": 7687273,
      "cover": "https://p26-sign.douyinpic.com/tos-cn-p-0015c000-ce/ogpSnEWIDzqT9B1LwEfpANDWhFekOqEAtqb9XL~noop.jpeg?lk3s=bfd515bb&x-expires=1783580400&x-signature=u1%2FEUw6dSY3tqpjpBfJsgCNvJYs%3D&from=3218412987",
      "link": "https://www.douyin.com/search/%E7%AE%A1%E6%B3%BD%E5%85%83%E5%86%8D%E7%8E%B0%E5%A7%86%E5%B7%B4%E4%BD%A9%E4%B9%8B%E5%89%91%E5%90%9F%E5%94%B1",
      "event_time": "2026/07/07 11:10:36",
      "event_time_at": 1783393836,
      "active_time": "2026-07-09 09:53:19",
      "active_time_at": 1783590799000
    },
    {
      "title": "知道你不能还要你感受",
      "hot_value": 7682882,
      "cover": "https://p5-ex-gddgtc-sign.douyinpic.com/tos-cn-i-0813/oEVQ3GDeIFAFQfEkuAEEA4BAByuWf7wSUSXCAW~noop.jpeg?lk3s=bfd515bb&x-expires=1783580400&x-signature=Ptw3b1p19a734gKCGG2XvA%2BWxk8%3D&from=3218412987",
      "link": "https://www.douyin.com/search/%E7%9F%A5%E9%81%93%E4%BD%A0%E4%B8%8D%E8%83%BD%E8%BF%98%E8%A6%81%E4%BD%A0%E6%84%9F%E5%8F%97",
      "event_time": "2026/07/07 17:02:19",
      "event_time_at": 1783414939,
      "active_time": "2026-07-09 09:53:19",
      "active_time_at": 1783590799000
    },
    {
      "title": "这个暑假我先吃为敬",
      "hot_value": 7681106,
      "cover": "https://p11-sign.douyinpic.com/tos-cn-p-0015c000-ce/oQerIPGpTAvQFR2ufIJAeDZAMDuGMLFbecw9HD~noop.jpeg?lk3s=bfd515bb&x-expires=1783580400&x-signature=Cr%2Fh3QPOreVOt%2BjxudUZWGCyqM4%3D&from=3218412987",
      "link": "https://www.douyin.com/search/%E8%BF%99%E4%B8%AA%E6%9A%91%E5%81%87%E6%88%91%E5%85%88%E5%90%83%E4%B8%BA%E6%95%AC",
      "event_time": "2026/07/08 11:20:45",
      "event_time_at": 1783480845,
      "active_time": "2026-07-09 09:53:19",
      "active_time_at": 1783590799000
    },
    {
      "title": "CHIQUITA跳舞爽到我了",
      "hot_value": 7680622,
      "cover": "https://p26-sign.douyinpic.com/tos-cn-p-0015c000-ce/ooEvv1wCEEfiAoieC9IA46AexIwP0v4OqRJEDB~noop.jpeg?lk3s=bfd515bb&x-expires=1783580400&x-signature=Xxrr955K%2B%2FFx7D2l89VXRMsjioo%3D&from=3218412987",
      "link": "https://www.douyin.com/search/CHIQUITA%E8%B7%B3%E8%88%9E%E7%88%BD%E5%88%B0%E6%88%91%E4%BA%86",
      "event_time": "2026/07/08 22:24:48",
      "event_time_at": 1783520688,
      "active_time": "2026-07-09 09:53:19",
      "active_time_at": 1783590799000
    },
    {
      "title": "张真源密室拥抱NPC第一人",
      "hot_value": 7673508,
      "cover": "https://p11-sign.douyinpic.com/tos-cn-p-0015/oowiQIL1rXAIkBx4iC0bKaNRRQIIvPPPtA3Ft~noop.jpeg?lk3s=bfd515bb&x-expires=1783580400&x-signature=IfmkG51xGfVgsErTpg1BhBDqOwg%3D&from=3218412987",
      "link": "https://www.douyin.com/search/%E5%BC%A0%E7%9C%9F%E6%BA%90%E5%AF%86%E5%AE%A4%E6%8B%A5%E6%8A%B1NPC%E7%AC%AC%E4%B8%80%E4%BA%BA",
      "event_time": "2026/07/08 15:46:18",
      "event_time_at": 1783496778,
      "active_time": "2026-07-09 09:53:19",
      "active_time_at": 1783590799000
    },
    {
      "title": "功夫女足心中那团火跳起来了",
      "hot_value": 7669752,
      "cover": "https://p11-sign.douyinpic.com/tos-cn-p-0015c000-ce/o080DsCsIEyWYfsEmwqAMDgBRQsjngjfwAnFC9~noop.jpeg?lk3s=bfd515bb&x-expires=1783580400&x-signature=4lFCPq5jvm8uURJunNNg7INjPZY%3D&from=3218412987",
      "link": "https://www.douyin.com/search/%E5%8A%9F%E5%A4%AB%E5%A5%B3%E8%B6%B3%E5%BF%83%E4%B8%AD%E9%82%A3%E5%9B%A2%E7%81%AB%E8%B7%B3%E8%B5%B7%E6%9D%A5%E4%BA%86",
      "event_time": "2026/07/08 13:35:54",
      "event_time_at": 1783488954,
      "active_time": "2026-07-09 09:53:19",
      "active_time_at": 1783590799000
    },
    {
      "title": "蓝战非探访亚速尔群岛",
      "hot_value": 7668647,
      "cover": "https://p3-sign.douyinpic.com/tos-cn-p-0015/ok5CaIsHMtUAJty2dKQwCWmB7BJMfA6aeI8Rey~noop.jpeg?lk3s=bfd515bb&x-expires=1783580400&x-signature=dRjrpnmuqfENj4JDdIf1vMOiUg0%3D&from=3218412987",
      "link": "https://www.douyin.com/search/%E8%93%9D%E6%88%98%E9%9D%9E%E6%8E%A2%E8%AE%BF%E4%BA%9A%E9%80%9F%E5%B0%94%E7%BE%A4%E5%B2%9B",
      "event_time": "2026/07/08 13:06:34",
      "event_time_at": 1783487194,
      "active_time": "2026-07-09 09:53:19",
      "active_time_at": 1783590799000
    },
    {
      "title": "和雷霆美食ride or die",
      "hot_value": 7667904,
      "cover": "https://p11-sign.douyinpic.com/tos-cn-i-0813c000-ce/oQPiWEA9L5AAAcoBBMxIGip0zzKmzaHP4akAi~noop.jpeg?lk3s=bfd515bb&x-expires=1783580400&x-signature=DSA4IR9KHQL%2FR9afmbxUvvySifY%3D&from=3218412987",
      "link": "https://www.douyin.com/search/%E5%92%8C%E9%9B%B7%E9%9C%86%E7%BE%8E%E9%A3%9Fride%20or%20die",
      "event_time": "2026/07/08 11:43:27",
      "event_time_at": 1783482207,
      "active_time": "2026-07-09 09:53:19",
      "active_time_at": 1783590799000
    },
    {
      "title": "谁懂涂鸦耳机的ins感",
      "hot_value": 7666427,
      "cover": "https://p3-sign.douyinpic.com/tos-cn-p-0015/ogZXCoeG0QOn2fpDI8HaCM7fZEjAfIIbLEkhQA~noop.jpeg?lk3s=bfd515bb&x-expires=1783580400&x-signature=yyFstHX8pj6xhmIOGUhKANONkdY%3D&from=3218412987",
      "link": "https://www.douyin.com/search/%E8%B0%81%E6%87%82%E6%B6%82%E9%B8%A6%E8%80%B3%E6%9C%BA%E7%9A%84ins%E6%84%9F",
      "event_time": "2026/07/08 14:47:58",
      "event_time_at": 1783493278,
      "active_time": "2026-07-09 09:53:19",
      "active_time_at": 1783590799000
    },
    {
      "title": "我最最最爱的你",
      "hot_value": 7665514,
      "cover": "https://p11-sign.douyinpic.com/tos-cn-i-0813c001/o8VgQIkxPBuAAAiRiImEYMJxIPAaBgFSbYi1A~noop.jpeg?lk3s=bfd515bb&x-expires=1783580400&x-signature=fZ%2BodyZFKc5D7qii3%2BnHwo3OU%2FA%3D&from=3218412987",
      "link": "https://www.douyin.com/search/%E6%88%91%E6%9C%80%E6%9C%80%E6%9C%80%E7%88%B1%E7%9A%84%E4%BD%A0",
      "event_time": "2026/07/08 14:26:41",
      "event_time_at": 1783492001,
      "active_time": "2026-07-09 09:53:19",
      "active_time_at": 1783590799000
    },
    {
      "title": "G2 3:1战胜T1",
      "hot_value": 7660261,
      "cover": "https://p3-sign.douyinpic.com/tos-cn-p-0015/oYAACsmNN31QqBHfX14v4IAECJ8esl9gHhVAWR~noop.jpeg?lk3s=bfd515bb&x-expires=1783580400&x-signature=x1QeR5GxMSMmZgjYIO0z9RUtPNU%3D&from=3218412987",
      "link": "https://www.douyin.com/search/G2%203%3A1%E6%88%98%E8%83%9CT1",
      "event_time": "2026/07/08 15:01:36",
      "event_time_at": 1783494096,
      "active_time": "2026-07-09 09:53:19",
      "active_time_at": 1783590799000
    },
    {
      "title": "陈异苗靖废墟初吻",
      "hot_value": 7659614,
      "cover": "https://p26-sign.douyinpic.com/tos-cn-p-0015/oECeAaumMXky3BjfBUQM9W8RAlfsARJCBE0767~noop.jpeg?lk3s=bfd515bb&x-expires=1783580400&x-signature=fhJIZ5fgH1iOLNjRDpdswH4%2BUn4%3D&from=3218412987",
      "link": "https://www.douyin.com/search/%E9%99%88%E5%BC%82%E8%8B%97%E9%9D%96%E5%BA%9F%E5%A2%9F%E5%88%9D%E5%90%BB",
      "event_time": "2026/07/08 11:23:24",
      "event_time_at": 1783481004,
      "active_time": "2026-07-09 09:53:19",
      "active_time_at": 1783590799000
    },
    {
      "title": "干什么都一个人会不会太厉害了",
      "hot_value": 7658155,
      "cover": "https://p26-sign.douyinpic.com/tos-cn-i-0813/oQEAL17AACZAjgeV59IABiiAtNBxSJAUDfUCoD~noop.jpeg?lk3s=bfd515bb&x-expires=1783580400&x-signature=ViNnCkIurWakr2Z7soSpct9m8JM%3D&from=3218412987",
      "link": "https://www.douyin.com/search/%E5%B9%B2%E4%BB%80%E4%B9%88%E9%83%BD%E4%B8%80%E4%B8%AA%E4%BA%BA%E4%BC%9A%E4%B8%8D%E4%BC%9A%E5%A4%AA%E5%8E%89%E5%AE%B3%E4%BA%86",
      "event_time": "2026/07/08 21:58:07",
      "event_time_at": 1783519087,
      "active_time": "2026-07-09 09:53:19",
      "active_time_at": 1783590799000
    },
    {
      "title": "苗靖想喝的海带绿豆汤是什么",
      "hot_value": 7656754,
      "cover": "https://p11-sign.douyinpic.com/tos-cn-p-0015c000-ce/oMTu9pfGwWaIDfL2HDgKe0Agl7AeYvSzuEMgpG~noop.jpeg?lk3s=bfd515bb&x-expires=1783580400&x-signature=hLEUU3DfrZBVXiso6IbsZRchOAg%3D&from=3218412987",
      "link": "https://www.douyin.com/search/%E8%8B%97%E9%9D%96%E6%83%B3%E5%96%9D%E7%9A%84%E6%B5%B7%E5%B8%A6%E7%BB%BF%E8%B1%86%E6%B1%A4%E6%98%AF%E4%BB%80%E4%B9%88",
      "event_time": "2026/07/07 21:29:07",
      "event_time_at": 1783430947,
      "active_time": "2026-07-09 09:53:19",
      "active_time_at": 1783590799000
    },
    {
      "title": "小个子的夏日氛围感穿搭",
      "hot_value": 7656747,
      "cover": "https://p11-sign.douyinpic.com/tos-cn-p-0015c000-ce/oYHVEDLSwRj9AEZJq7IViFFzAYEIeNf1CeBuDw~noop.jpeg?lk3s=bfd515bb&x-expires=1783580400&x-signature=7OM7qf36dyvE%2FkoE3x6NdKfJ2sE%3D&from=3218412987",
      "link": "https://www.douyin.com/search/%E5%B0%8F%E4%B8%AA%E5%AD%90%E7%9A%84%E5%A4%8F%E6%97%A5%E6%B0%9B%E5%9B%B4%E6%84%9F%E7%A9%BF%E6%90%AD",
      "event_time": "2026/07/07 15:08:05",
      "event_time_at": 1783408085,
      "active_time": "2026-07-09 09:53:19",
      "active_time_at": 1783590799000
    },
    {
      "title": "开始追更“三只小猪和贵人鸟”",
      "hot_value": 7654194,
      "cover": "https://p3-sign.douyinpic.com/tos-cn-p-0015/o4S5A0fDNEg19fqAJZG3NRD2HBYAlEPWFAiCIg~noop.jpeg?lk3s=bfd515bb&x-expires=1783580400&x-signature=L%2BIDhcPb9FiSP4Nq4wbdTCzIvOE%3D&from=3218412987",
      "link": "https://www.douyin.com/search/%E5%BC%80%E5%A7%8B%E8%BF%BD%E6%9B%B4%E2%80%9C%E4%B8%89%E5%8F%AA%E5%B0%8F%E7%8C%AA%E5%92%8C%E8%B4%B5%E4%BA%BA%E9%B8%9F%E2%80%9D",
      "event_time": "2026/07/08 21:07:58",
      "event_time_at": 1783516078,
      "active_time": "2026-07-09 09:53:19",
      "active_time_at": 1783590799000
    },
    {
      "title": "株洲菜从来没让我失望过",
      "hot_value": 7651351,
      "cover": "https://p3-sign.douyinpic.com/tos-cn-p-0015c000-ce/o0wiKEMvqEq90b9lADBJZttTFE8EnIf9LATNMe~noop.jpeg?lk3s=bfd515bb&x-expires=1783580400&x-signature=3iwAf13aq3GcaYD6awypbe6jEgA%3D&from=3218412987",
      "link": "https://www.douyin.com/search/%E6%A0%AA%E6%B4%B2%E8%8F%9C%E4%BB%8E%E6%9D%A5%E6%B2%A1%E8%AE%A9%E6%88%91%E5%A4%B1%E6%9C%9B%E8%BF%87",
      "event_time": "2026/07/08 16:40:35",
      "event_time_at": 1783500035,
      "active_time": "2026-07-09 09:53:19",
      "active_time_at": 1783590799000
    },
    {
      "title": "来中山就为了这口乳鸽宴",
      "hot_value": 7646356,
      "cover": "https://p3-sign.douyinpic.com/tos-cn-p-0015/o0AIgFBqsXiqEwHr4PuQR7irI7OvkaNjAlBIW~noop.jpeg?lk3s=bfd515bb&x-expires=1783580400&x-signature=32RFGT%2FB6MT4rI2h9nSM8SKm6MI%3D&from=3218412987",
      "link": "https://www.douyin.com/search/%E6%9D%A5%E4%B8%AD%E5%B1%B1%E5%B0%B1%E4%B8%BA%E4%BA%86%E8%BF%99%E5%8F%A3%E4%B9%B3%E9%B8%BD%E5%AE%B4",
      "event_time": "2026/07/08 18:01:36",
      "event_time_at": 1783504896,
      "active_time": "2026-07-09 09:53:19",
      "active_time_at": 1783590799000
    },
    {
      "title": "带你第一视角体验溪降",
      "hot_value": 7645800,
      "cover": "https://p3-sign.douyinpic.com/tos-cn-p-0015/o0EoMPDPIzkIBw49TQvinijRuQBaEkAAAOTi1~noop.jpeg?lk3s=bfd515bb&x-expires=1783580400&x-signature=cJjVVqaDNHH1JEgVyaZy74YKJeU%3D&from=3218412987",
      "link": "https://www.douyin.com/search/%E5%B8%A6%E4%BD%A0%E7%AC%AC%E4%B8%80%E8%A7%86%E8%A7%92%E4%BD%93%E9%AA%8C%E6%BA%AA%E9%99%8D",
      "event_time": "2026/07/08 09:24:58",
      "event_time_at": 1783473898,
      "active_time": "2026-07-09 09:53:19",
      "active_time_at": 1783590799000
    }
  ],
  "code": 200,
  "message": "获取成功。当前部署平台已迁移到 Cloudflare Workers，如有问题请及时反馈。开源地址 https://github.com/vikiboss/60s，反馈群 595941841。"
}