{
  "source": {
    "name": "今日头条",
    "description": "头条热榜",
    "url": "https://60s.viki.moe/v2/toutiao",
    "lastUpdate": "2026-02-23T12:38:48.245Z"
  },
  "data": [
    {
      "title": "高速交警硬核喊话慢速车",
      "hot_value": 28942641,
      "cover": "https://p3-sign.toutiaoimg.com/tos-cn-i-qvj2lq49k0/fbd7728dd9384e4e844d8f67974a080a~tplv-tt-shrink:960:540.jpeg?_iz=30575&from=sign_default&lk3s=8d617dac&x-expires=1774396800&x-signature=RNBiqIAkLcrl%2BUmBzs7wPz6WHjQ%3D",
      "link": "https://www.toutiao.com/trending/7609295690623713343"
    },
    {
      "title": "德国总理默茨将访华",
      "hot_value": 26188384,
      "cover": "https://p3-sign.toutiaoimg.com/top-static-files-outer/breaknews/44f9b09f-079c-414e-8a69-4e08c08a3858~tplv-tt-shrink:960:540.jpeg?_iz=30575&from=sign_default&lk3s=8d617dac&x-expires=1774396800&x-signature=z80EXV3THqgcXSIgCPqJ1f8qa5Y%3D",
      "link": "https://www.toutiao.com/trending/7609512007510822441"
    },
    {
      "title": "今年春节都有哪些新图景",
      "hot_value": 23696230,
      "cover": "https://p3-sign.toutiaoimg.com/mosaic-legacy/2b29000036f8405561443~tplv-tt-shrink:960:540.jpeg?_iz=30575&from=sign_default&lk3s=8d617dac&x-expires=1774396800&x-signature=YfXXClJ4PlUzxG4I%2FFMRaN5tVXw%3D",
      "link": "https://www.toutiao.com/article/7609845926697419298"
    },
    {
      "title": "被击毙的全球头号毒枭是何许人",
      "hot_value": 21441236,
      "cover": "https://p3-sign.toutiaoimg.com/tos-cn-i-qvj2lq49k0/0dbc25cbf3dd4331b3f767c87790e333~tplv-tt-shrink:960:540.jpeg?_iz=30575&from=sign_default&lk3s=8d617dac&x-expires=1774396800&x-signature=M473U5v5TD6Regxh4Iwx5RjrD6c%3D",
      "link": "https://www.toutiao.com/trending/7609994728805027338"
    },
    {
      "title": "西安大雪",
      "hot_value": 19400832,
      "cover": "https://p3-sign.toutiaoimg.com/top-static-files-outer/breaknews/58aaa485-4da7-4577-83b5-bac9ce7e9630~tplv-tt-shrink:960:540.jpeg?_iz=30575&from=sign_default&lk3s=8d617dac&x-expires=1774396800&x-signature=7jIE31tWohzErjxTApoCUtUk30Q%3D",
      "link": "https://www.toutiao.com/trending/7609910890398187558"
    },
    {
      "title": "尼格买提家宴8个菜没一个青菜",
      "hot_value": 17554599,
      "cover": "https://p3-sign.toutiaoimg.com/tos-cn-i-qvj2lq49k0/62c21396a6314469a1a35279c8de3eaf~tplv-tt-shrink:960:540.jpeg?_iz=30575&from=sign_default&lk3s=8d617dac&x-expires=1774396800&x-signature=2iPUOD7bSwYvm%2F0hWp6woUOhWQg%3D",
      "link": "https://www.toutiao.com/trending/7608984641257127942"
    },
    {
      "title": "高速堵车亲历者：10小时路程开两天",
      "hot_value": 15884058,
      "cover": "https://p3-sign.toutiaoimg.com/tos-cn-i-qvj2lq49k0/11047d54ddcf445a9372bad39e8849b0~tplv-tt-shrink:960:540.jpeg?_iz=30575&from=sign_default&lk3s=8d617dac&x-expires=1774396800&x-signature=rupQQNOjiHp1ZMnwGIDgTk%2By8lA%3D",
      "link": "https://www.toutiao.com/trending/7609356676797939753"
    },
    {
      "title": "西安大唐不夜城有多火",
      "hot_value": 14372490,
      "cover": "https://p3-sign.toutiaoimg.com/tos-cn-i-qvj2lq49k0/2e4203d3520545b497037f991cfac606~tplv-tt-shrink:960:540.jpeg?_iz=30575&from=sign_default&lk3s=8d617dac&x-expires=1774396800&x-signature=BJeH2Ib8K7MMNjvNn9smXEHm%2F4U%3D",
      "link": "https://www.toutiao.com/trending/7609750050369617983"
    },
    {
      "title": "36斤活羊烤完剩6.9斤 商家称正常",
      "hot_value": 13004767,
      "cover": "https://p3-sign.toutiaoimg.com/tos-cn-i-qvj2lq49k0/d261146a9adb4bd8884cd31272158e8b~tplv-tt-shrink:960:540.jpeg?_iz=30575&from=sign_default&lk3s=8d617dac&x-expires=1774396800&x-signature=sF%2FQtsOBzAlRe9QW4UMmg%2BQNoEg%3D",
      "link": "https://www.toutiao.com/trending/7609940688633446406"
    },
    {
      "title": "广东一高速春运期间可逆行且合规",
      "hot_value": 11767199,
      "cover": "https://p26-sign.toutiaoimg.com/tos-cn-i-qvj2lq49k0/af0934623f41480fa831c422ae0b1121~tplv-tt-shrink:960:540.jpeg?_iz=30575&from=sign_default&lk3s=8d617dac&x-expires=1774396800&x-signature=PuwKMPrDLTJDOVCNBb5RZjF1rk0%3D",
      "link": "https://www.toutiao.com/trending/7609133902992801811"
    },
    {
      "title": "保鲜膜裹食物加热会致癌系谣言",
      "hot_value": 10647402,
      "cover": "https://p26-sign.toutiaoimg.com/tos-cn-i-qvj2lq49k0/92a919a61a834b16956f1b7d0a3b904d~tplv-tt-shrink:960:540.jpeg?_iz=30575&from=sign_default&lk3s=8d617dac&x-expires=1774396800&x-signature=CIQAXpCwJ95KP1KO6Kp7g%2FUvhBQ%3D",
      "link": "https://www.toutiao.com/trending/7609613496015470630"
    },
    {
      "title": "比特币价格为何瀑布式下跌",
      "hot_value": 9634168,
      "cover": "https://p3-sign.toutiaoimg.com/tos-cn-i-qvj2lq49k0/a4dd8c84d25e42e2a360de0ec5426010~tplv-tt-shrink:960:540.jpeg?_iz=30575&from=sign_default&lk3s=8d617dac&x-expires=1774396800&x-signature=O06%2BUNDe1N%2FZ7JTk9lhKnUqx5RE%3D",
      "link": "https://www.toutiao.com/trending/7609967033089789467"
    },
    {
      "title": "女子1人喝倒全家5个男人",
      "hot_value": 8717356,
      "cover": "https://p3-sign.toutiaoimg.com/tos-cn-i-qvj2lq49k0/d09b2a6424e044f8a5b61592353754eb~tplv-tt-shrink:960:540.jpeg?_iz=30575&from=sign_default&lk3s=8d617dac&x-expires=1774396800&x-signature=btIJX1EPmC6NqOgqMAIhUxZVLCc%3D",
      "link": "https://www.toutiao.com/trending/7609625766141149226"
    },
    {
      "title": "外籍博主称“终于体验了春节堵车”",
      "hot_value": 7887789,
      "cover": "https://p26-sign.toutiaoimg.com/tos-cn-i-qvj2lq49k0/cec4cc57fc094491b2d05eb971af5411~tplv-tt-shrink:960:540.jpeg?_iz=30575&from=sign_default&lk3s=8d617dac&x-expires=1774396800&x-signature=X0Im%2BIijS28xECn6ruX%2BiTIWGFY%3D",
      "link": "https://www.toutiao.com/trending/7609215105083801641"
    },
    {
      "title": "谷爱凌晒金牌霸气回怼外媒挑衅",
      "hot_value": 7137167,
      "cover": "https://p3-sign.toutiaoimg.com/tos-cn-i-qvj2lq49k0/7a87db12aa5845fdba3821821290de6a~tplv-tt-shrink:960:540.jpeg?_iz=30575&from=sign_default&lk3s=8d617dac&x-expires=1774396800&x-signature=IBllx4t9FAECceXket1MX3lw%2Fhg%3D",
      "link": "https://www.toutiao.com/trending/7609889348103900681"
    },
    {
      "title": "广西农民为何热衷种甘蔗",
      "hot_value": 6457976,
      "cover": "https://p3-sign.toutiaoimg.com/tos-cn-i-qvj2lq49k0/0decbb3544dd482fb845ad0f0af52503~tplv-tt-shrink:960:540.jpeg?_iz=30575&from=sign_default&lk3s=8d617dac&x-expires=1774396800&x-signature=owyn%2F2HAl7%2B8s11RYKi5KFYZqQk%3D",
      "link": "https://www.toutiao.com/trending/7609788836637343798"
    },
    {
      "title": "“大聪明”们半夜出发全堵高速上了",
      "hot_value": 5843418,
      "cover": "https://p3-sign.toutiaoimg.com/tos-cn-i-qvj2lq49k0/9ba1a298f88146e48a8fc25c01d5361e~tplv-tt-shrink:960:540.jpeg?_iz=30575&from=sign_default&lk3s=8d617dac&x-expires=1774396800&x-signature=b8cTBVyUmLYsarg1q0tIvni2%2FIA%3D",
      "link": "https://www.toutiao.com/trending/7609654368803668018"
    },
    {
      "title": "越野爱好者骑坐式独轮车攀爬陡峭山坡",
      "hot_value": 5287343,
      "cover": "https://p3-sign.toutiaoimg.com/tos-cn-i-qvj2lq49k0/8ee3bcbf88f545e4b4de6d177794ad25~tplv-tt-shrink:960:540.jpeg?_iz=30575&from=sign_default&lk3s=8d617dac&x-expires=1774396800&x-signature=HFG1C9fQXf87%2BdeEVeV8YKBnHoY%3D",
      "link": "https://www.toutiao.com/trending/7609954554201997331"
    },
    {
      "title": "《镖人》连续4天票房逆跌",
      "hot_value": 4784186,
      "cover": "https://p3-sign.toutiaoimg.com/tos-cn-i-qvj2lq49k0/cf59b92292214738a5f5e3812ab9ad82~tplv-tt-shrink:960:540.jpeg?_iz=30575&from=sign_default&lk3s=8d617dac&x-expires=1774396800&x-signature=iBzHBz4VVsQsbeCnOX%2BC1L0mb6E%3D",
      "link": "https://www.toutiao.com/trending/7608906613285453862"
    },
    {
      "title": "目击墨西哥暴力骚乱的中国游客发声",
      "hot_value": 4328910,
      "cover": "https://p3-sign.toutiaoimg.com/tos-cn-i-qvj2lq49k0/61ee4410f71f4a4aaaa5c6eb29789cf0~tplv-tt-shrink:960:540.jpeg?_iz=30575&from=sign_default&lk3s=8d617dac&x-expires=1774396800&x-signature=jIypj9I%2B4a3y1cEOaZLItZasUhM%3D",
      "link": "https://www.toutiao.com/trending/7609832476374024235"
    },
    {
      "title": "第一批返程的人已堵哭",
      "hot_value": 3916960,
      "cover": "https://p3-sign.toutiaoimg.com/tos-cn-i-qvj2lq49k0/609e4ab9aec3454a83b5c1a3d7fb01fc~tplv-tt-shrink:960:540.jpeg?_iz=30575&from=sign_default&lk3s=8d617dac&x-expires=1774396800&x-signature=wracp39SHFiIL1SYurduqjdJmCw%3D",
      "link": "https://www.toutiao.com/trending/7608778315033280548"
    },
    {
      "title": "杨幂：插足别人婚姻是错误的",
      "hot_value": 3544212,
      "cover": "https://p3-sign.toutiaoimg.com/tos-cn-i-qvj2lq49k0/cbd54ddb08c247398d716350c5361699~tplv-tt-shrink:960:540.jpeg?_iz=30575&from=sign_default&lk3s=8d617dac&x-expires=1774396800&x-signature=4fWpJK%2BrRm9uFGj9DZgDQdadd3I%3D",
      "link": "https://www.toutiao.com/trending/7609239787178065961"
    },
    {
      "title": "A股明天能否收获“开门红”",
      "hot_value": 3206936,
      "cover": "https://p3-sign.toutiaoimg.com/tos-cn-i-qvj2lq49k0/d19f8a1f5b9b445db27b94c2be27f924~tplv-tt-shrink:960:540.jpeg?_iz=30575&from=sign_default&lk3s=8d617dac&x-expires=1774396800&x-signature=8f%2FZBjRJTzh7j76Ml1Sw2IIoDKA%3D",
      "link": "https://www.toutiao.com/trending/7609548185849200650"
    },
    {
      "title": "墨西哥毒枭之死引贩毒集团疯狂报复",
      "hot_value": 2901755,
      "cover": "https://p3-sign.toutiaoimg.com/tos-cn-i-qvj2lq49k0/e515d68960584cb78da8b3931b2db5cf~tplv-tt-shrink:960:540.jpeg?_iz=30575&from=sign_default&lk3s=8d617dac&x-expires=1774396800&x-signature=WtcGDbbbSYWkBi6PK6sIdB2VbTw%3D",
      "link": "https://www.toutiao.com/trending/7609919504843394587"
    },
    {
      "title": "媒体：公职身份从来不是炫富资本",
      "hot_value": 2625617,
      "cover": "https://p3-sign.toutiaoimg.com/tos-cn-i-qvj2lq49k0/4a5ec9ae40c24ae88363c7f3a92a9828~tplv-tt-shrink:960:540.jpeg?_iz=30575&from=sign_default&lk3s=8d617dac&x-expires=1774396800&x-signature=an7Km%2FrSf7Y65wjRt%2BtaxLY6kBU%3D",
      "link": "https://www.toutiao.com/trending/7609515600783736882"
    },
    {
      "title": "游客在蜈支洲岛偶遇章子怡",
      "hot_value": 2375756,
      "cover": "https://p3-sign.toutiaoimg.com/tos-cn-i-qvj2lq49k0/7951b4818e4f44c7a3260a7efef07a0f~tplv-tt-shrink:960:540.jpeg?_iz=30575&from=sign_default&lk3s=8d617dac&x-expires=1774396800&x-signature=Vclxxc2avjWzF7OYB1iCPtP%2F3cU%3D",
      "link": "https://www.toutiao.com/trending/7609150769606852644"
    },
    {
      "title": "梅婷再演“父母爱情”",
      "hot_value": 2149673,
      "cover": "https://p3-sign.toutiaoimg.com/tos-cn-i-qvj2lq49k0/e30f08ad0d9e48c0a998fec1d852c0b8~tplv-tt-shrink:960:540.jpeg?_iz=30575&from=sign_default&lk3s=8d617dac&x-expires=1774396800&x-signature=ElYGXc5389854V%2Bdcs%2BfDQVS1ks%3D",
      "link": "https://www.toutiao.com/trending/7608888277487124523"
    },
    {
      "title": "航拍中国最大高速收费站返程高峰",
      "hot_value": 1945105,
      "cover": "https://p3-sign.toutiaoimg.com/tos-cn-i-qvj2lq49k0/d979288efe044056a67ffa72e02121ae~tplv-tt-shrink:960:540.jpeg?_iz=30575&from=sign_default&lk3s=8d617dac&x-expires=1774396800&x-signature=Rzn7unP8LkUtGhS5ghpLBVUV8U4%3D",
      "link": "https://www.toutiao.com/trending/7609944271609187850"
    },
    {
      "title": "科研员出国被策反：对方多次请吃烧烤",
      "hot_value": 1760003,
      "cover": "https://p3-sign.toutiaoimg.com/tos-cn-i-qvj2lq49k0/9e14d07302994f03a99887eab2510ddb~tplv-tt-shrink:960:540.jpeg?_iz=30575&from=sign_default&lk3s=8d617dac&x-expires=1774396800&x-signature=geK92dTWBrHGP97R%2BvJPEy1okKI%3D",
      "link": "https://www.toutiao.com/trending/7609939489301364782"
    },
    {
      "title": "哈尔滨300多只东北虎轮流“轻断食”",
      "hot_value": 1592517,
      "cover": "https://p3-sign.toutiaoimg.com/tos-cn-i-qvj2lq49k0/cf2523ad52ed426483bfb13f7b16ee4f~tplv-tt-shrink:960:540.jpeg?_iz=30575&from=sign_default&lk3s=8d617dac&x-expires=1774396800&x-signature=5VOBlYeQT4tY6VMWbpcEwuHNDMw%3D",
      "link": "https://www.toutiao.com/trending/7609561793375764534"
    },
    {
      "title": "四大航司增加海南航班",
      "hot_value": 1440969,
      "cover": "https://p3-sign.toutiaoimg.com/top-static-files-outer/breaknews/f0f24be8-6425-4f34-9868-08fc2f4f8b92~tplv-tt-shrink:960:540.jpeg?_iz=30575&from=sign_default&lk3s=8d617dac&x-expires=1774396800&x-signature=bbnHPCtw1%2ByVMbBKLDfpo9Nx%2FtU%3D",
      "link": "https://www.toutiao.com/trending/7609703294411456548"
    },
    {
      "title": "30余人欢聚不过2小时 男子看监控落泪",
      "hot_value": 1303842,
      "cover": "https://p3-sign.toutiaoimg.com/tos-cn-i-qvj2lq49k0/294b3fc2a5d847f98eeb0ee645e8a318~tplv-tt-shrink:960:540.jpeg?_iz=30575&from=sign_default&lk3s=8d617dac&x-expires=1774396800&x-signature=%2Fyaio3wswICznxql0%2FXptT1fBQg%3D",
      "link": "https://www.toutiao.com/trending/7609133409910312490"
    },
    {
      "title": "6旬大爷初学摩托失控撞倒55岁弟弟",
      "hot_value": 1179765,
      "cover": "https://p3-sign.toutiaoimg.com/tos-cn-i-qvj2lq49k0/f50ed740e4a548ad8d28bac9cc3a0660~tplv-tt-shrink:960:540.jpeg?_iz=30575&from=sign_default&lk3s=8d617dac&x-expires=1774396800&x-signature=P6KJiETxg2YPLNg40bi1pxCQhWs%3D",
      "link": "https://www.toutiao.com/trending/7609592775939735595"
    },
    {
      "title": "各地春节返程高峰人潮车流如织",
      "hot_value": 1067496,
      "cover": "https://p3-sign.toutiaoimg.com/tos-cn-i-qvj2lq49k0/6392c34225be4f8a95febd14f5314cdb~tplv-tt-shrink:960:540.jpeg?_iz=30575&from=sign_default&lk3s=8d617dac&x-expires=1774396800&x-signature=k0A7VWqyNee0uvHmEtu4J5lmwek%3D",
      "link": "https://www.toutiao.com/trending/7609247229958209579"
    },
    {
      "title": "陈妍希夸林心如女儿太漂亮了",
      "hot_value": 965910,
      "cover": "https://p3-sign.toutiaoimg.com/tos-cn-i-qvj2lq49k0/97c2c36fb6374d23a85cd28eb024b104~tplv-tt-shrink:960:540.jpeg?_iz=30575&from=sign_default&lk3s=8d617dac&x-expires=1774396800&x-signature=nWJkoYf24BHMkl%2Bg93doo8w370g%3D",
      "link": "https://www.toutiao.com/trending/7609859204752523314"
    },
    {
      "title": "谷爱凌“炸”完赛场忙秀场",
      "hot_value": 873992,
      "cover": "https://p3-sign.toutiaoimg.com/tos-cn-i-qvj2lq49k0/a2f14e6b90e245988448e930acf91a50~tplv-tt-shrink:960:540.jpeg?_iz=30575&from=sign_default&lk3s=8d617dac&x-expires=1774396800&x-signature=aV7Z4RVdpNt6M1VmCsDzpOTbVK8%3D",
      "link": "https://www.toutiao.com/trending/7608855470317010980"
    },
    {
      "title": "山东蓬莱“宰客”酒楼招牌被强拆",
      "hot_value": 790820,
      "cover": "https://p3-sign.toutiaoimg.com/tos-cn-i-qvj2lq49k0/a8730c708ac54a20b485ba9107a4c90c~tplv-tt-shrink:960:540.jpeg?_iz=30575&from=sign_default&lk3s=8d617dac&x-expires=1774396800&x-signature=IVrSsevIIxo1nOq9eZ9S9F1LjAE%3D",
      "link": "https://www.toutiao.com/trending/7609902350228029494"
    },
    {
      "title": "电影《镖人》最大看点是什么",
      "hot_value": 715564,
      "cover": "https://p3-sign.toutiaoimg.com/tos-cn-i-qvj2lq49k0/0730f948af51485f83add4efb8623321~tplv-tt-shrink:960:540.jpeg?_iz=30575&from=sign_default&lk3s=8d617dac&x-expires=1774396800&x-signature=%2BYPuM7PIey1XaUqrSgLAPpSgfd4%3D",
      "link": "https://www.toutiao.com/trending/7610000492743101998"
    },
    {
      "title": "货车起火 众人误以为爆炸紧急躲避",
      "hot_value": 647469,
      "cover": "https://p3-sign.toutiaoimg.com/tos-cn-i-qvj2lq49k0/922abcc7989f40e8a1ab9d6c7fee2466~tplv-tt-shrink:960:540.jpeg?_iz=30575&from=sign_default&lk3s=8d617dac&x-expires=1774396800&x-signature=f2x1c5FSQNwGpWKLpU2cqaszs1E%3D",
      "link": "https://www.toutiao.com/trending/7609628500248526884"
    },
    {
      "title": "四川女婿黄子韬在家也得穿省服",
      "hot_value": 585854,
      "cover": "https://p3-sign.toutiaoimg.com/tos-cn-i-qvj2lq49k0/debca065969c4266962091df210ebcb1~tplv-tt-shrink:960:540.jpeg?_iz=30575&from=sign_default&lk3s=8d617dac&x-expires=1774396800&x-signature=19D2khUtiEEK8y28ynLNR9ecpGc%3D",
      "link": "https://www.toutiao.com/trending/7609134542070366271"
    },
    {
      "title": "为何说大年初七是所有人的生日",
      "hot_value": 530102,
      "cover": "https://p3-sign.toutiaoimg.com/top-static-files-outer/breaknews/b45fdfa5-528e-40d7-8df5-df0539e2361f~tplv-tt-shrink:960:540.jpeg?_iz=30575&from=sign_default&lk3s=8d617dac&x-expires=1774396800&x-signature=%2BWkcFV5FqqQ8s17acFCj9lxAQM4%3D",
      "link": "https://www.toutiao.com/trending/7608833243450212398"
    },
    {
      "title": "莆田电视台回应黑龙江游客是福建口音",
      "hot_value": 479657,
      "cover": "https://p3-sign.toutiaoimg.com/tos-cn-i-qvj2lq49k0/774b8851d79040f393d13fa92c17abd0~tplv-tt-shrink:960:540.jpeg?_iz=30575&from=sign_default&lk3s=8d617dac&x-expires=1774396800&x-signature=bR0mrT3nFvUexxdhFvQdEpAhgUs%3D",
      "link": "https://www.toutiao.com/trending/7609810377287106610"
    },
    {
      "title": "10余名女兵24小时控守“电磁大门”",
      "hot_value": 434011,
      "cover": "https://p3-sign.toutiaoimg.com/tos-cn-i-qvj2lq49k0/03dde67b613c467c9d8fd78dd41df0c4~tplv-tt-shrink:960:540.jpeg?_iz=30575&from=sign_default&lk3s=8d617dac&x-expires=1774396800&x-signature=IO4qrNJzgeXXU6a3rgtbkniiDv0%3D",
      "link": "https://www.toutiao.com/trending/7609219403708448810"
    },
    {
      "title": "伊朗：将誓死捍卫国家独立和主权完整",
      "hot_value": 392709,
      "cover": "https://p3-sign.toutiaoimg.com/tos-cn-i-qvj2lq49k0/881fd900fb2c44349745b6cb7a7a5666~tplv-tt-shrink:960:540.jpeg?_iz=30575&from=sign_default&lk3s=8d617dac&x-expires=1774396800&x-signature=7SyDqmIe5iwm8t5zf1DBAZwgRXA%3D",
      "link": "https://www.toutiao.com/trending/7609028906888445958"
    },
    {
      "title": "返程前的告别看泪目了",
      "hot_value": 355338,
      "cover": "https://p3-sign.toutiaoimg.com/tos-cn-i-qvj2lq49k0/fd5f66a6ba9f4f1ea14323ebf698cfb4~tplv-tt-shrink:960:540.jpeg?_iz=30575&from=sign_default&lk3s=8d617dac&x-expires=1774396800&x-signature=OnYaF3mftQqsx04E93SwBJ9W4e4%3D",
      "link": "https://www.toutiao.com/trending/7609133409910279722"
    },
    {
      "title": "贺希宁王浩然随中国男篮冲刺世预赛",
      "hot_value": 321523,
      "cover": "https://p3-sign.toutiaoimg.com/mosaic-legacy/2b29000036f8405561443~tplv-tt-shrink:960:540.jpeg?_iz=30575&from=sign_default&lk3s=8d617dac&x-expires=1774396800&x-signature=YfXXClJ4PlUzxG4I%2FFMRaN5tVXw%3D",
      "link": "https://www.toutiao.com/trending/7609492964414488627"
    },
    {
      "title": "专家：以色列难主导中东局势",
      "hot_value": 290926,
      "cover": "https://p3-sign.toutiaoimg.com/tos-cn-i-qvj2lq49k0/c3308ad713cd4a91b411a27e3a953844~tplv-tt-shrink:960:540.jpeg?_iz=30575&from=sign_default&lk3s=8d617dac&x-expires=1774396800&x-signature=NZE2NsSnJRS2H%2F9Pq7sIco9uAsE%3D",
      "link": "https://www.toutiao.com/trending/7610000431304936987"
    },
    {
      "title": "鸿蒙智行问界M6银色实车现身",
      "hot_value": 263241,
      "cover": "https://p3-sign.toutiaoimg.com/tos-cn-i-qvj2lq49k0/676adcb53a0546369a8596ab27f0d1c2~tplv-tt-shrink:960:540.jpeg?_iz=30575&from=sign_default&lk3s=8d617dac&x-expires=1774396800&x-signature=xgbBcUsmqxkEp3Ef0Qjfdj3syjQ%3D",
      "link": "https://www.toutiao.com/trending/7609630522524925958"
    },
    {
      "title": "包头街头出现北重集团轮式突击炮",
      "hot_value": 238190,
      "cover": "https://p3-sign.toutiaoimg.com/tos-cn-i-qvj2lq49k0/145da6d0098a4b8e81a4f5782855e2e3~tplv-tt-shrink:960:540.jpeg?_iz=30575&from=sign_default&lk3s=8d617dac&x-expires=1774396800&x-signature=kBF%2FFp9Ae8Ucqqn69ZK46o5harI%3D",
      "link": "https://www.toutiao.com/trending/7609650308562419763"
    },
    {
      "title": "网友把老虎拍得比山大",
      "hot_value": 215523,
      "cover": "https://p3-sign.toutiaoimg.com/tos-cn-i-qvj2lq49k0/d470bb52b46d4cfbbcf65bd2b4ebf041~tplv-tt-shrink:960:540.jpeg?_iz=30575&from=sign_default&lk3s=8d617dac&x-expires=1774396800&x-signature=3xiDnFhKeQ5WQXNSAXqBgITkb%2Bc%3D",
      "link": "https://www.toutiao.com/trending/7609888419339288639"
    }
  ],
  "code": 200,
  "message": "获取成功，开源地址 https://github.com/vikiboss/60s，反馈群 595941841"
}