{
  "source": {
    "name": "今日头条",
    "description": "头条热榜",
    "url": "https://60s.viki.moe/v2/toutiao",
    "lastUpdate": "2025-12-10T04:25:26.079Z"
  },
  "data": [
    {
      "title": "“最快女护士”以虚假理由调休被处分",
      "hot_value": 35609148,
      "cover": "https://p3-sign.toutiaoimg.com/tos-cn-i-qvj2lq49k0/15b3ba411ec74c51a31d72751a8a1e17~tplv-tt-shrink:960:540.jpeg?_iz=30575&from=sign_default&lk3s=8d617dac&x-expires=1767916800&x-signature=uX7gcZldtjVdyU8De3ZwvaLWKks%3D",
      "link": "https://www.toutiao.com/trending/7581014996018200617"
    },
    {
      "title": "日本地震是中国制造的？日方辟谣",
      "hot_value": 32220489,
      "cover": "https://p3-sign.toutiaoimg.com/tos-cn-i-qvj2lq49k0/512ac1035b8547f08160ba3b6e0172d0~tplv-tt-shrink:960:540.jpeg?_iz=30575&from=sign_default&lk3s=8d617dac&x-expires=1767916800&x-signature=izcUolm6znt3%2BCFIO6mvCCG%2BgsI%3D",
      "link": "https://www.toutiao.com/trending/7582045989461200410"
    },
    {
      "title": "文旅赋能消费升级",
      "hot_value": 29154304,
      "cover": "https://p3-sign.toutiaoimg.com/tos-cn-i-qvj2lq49k0/ffb4a8d440944f47a4b15ef3dba7d410~tplv-tt-shrink:960:540.jpeg?_iz=30575&from=sign_default&lk3s=8d617dac&x-expires=1767916800&x-signature=305rMVp4YnWi9TWVnwqpSg7Pn9s%3D",
      "link": "https://www.toutiao.com/article/7581730345557443118"
    },
    {
      "title": "广东汕头火灾遇难人数升至12人",
      "hot_value": 26379905,
      "cover": "https://p3-sign.toutiaoimg.com/mosaic-legacy/2b29000036f8405561443~tplv-tt-shrink:960:540.jpeg?_iz=30575&from=sign_default&lk3s=8d617dac&x-expires=1767916800&x-signature=uEjRJ6d%2BVqtVEkBNNU9PDl2A8pY%3D",
      "link": "https://www.toutiao.com/trending/7582073870828752430"
    },
    {
      "title": "国台办批赖清德妄称帮大陆解决问题",
      "hot_value": 23869525,
      "cover": "https://p3-sign.toutiaoimg.com/mosaic-legacy/2b29000036f8405561443~tplv-tt-shrink:960:540.jpeg?_iz=30575&from=sign_default&lk3s=8d617dac&x-expires=1767916800&x-signature=uEjRJ6d%2BVqtVEkBNNU9PDl2A8pY%3D",
      "link": "https://www.toutiao.com/trending/7581802340237443082"
    },
    {
      "title": "为何要全面禁产水银体温计",
      "hot_value": 21598040,
      "cover": "https://p3-sign.toutiaoimg.com/tos-cn-i-qvj2lq49k0/86f6ecec4b794c959fce444b9c6ddf68~tplv-tt-shrink:960:540.jpeg?_iz=30575&from=sign_default&lk3s=8d617dac&x-expires=1767916800&x-signature=TPuK5d%2BD%2BJ2z7eqsRatBbEkHSOc%3D",
      "link": "https://www.toutiao.com/trending/7582004723851726382"
    },
    {
      "title": "韩国硬刚高市早苗",
      "hot_value": 19542714,
      "cover": "https://p3-sign.toutiaoimg.com/top-static-files-outer/breaknews/c6ea236f-97f3-4944-b53a-3ffb81128a85~tplv-tt-shrink:960:540.jpeg?_iz=30575&from=sign_default&lk3s=8d617dac&x-expires=1767916800&x-signature=qKs5Tc%2FxvPYwLe%2FzItlnlAeTG3c%3D",
      "link": "https://www.toutiao.com/trending/7581875636403273747"
    },
    {
      "title": "国台办批赖清德称没必要宣布“台独”",
      "hot_value": 17682979,
      "cover": "https://p3-sign.toutiaoimg.com/mosaic-legacy/2b29000036f8405561443~tplv-tt-shrink:960:540.jpeg?_iz=30575&from=sign_default&lk3s=8d617dac&x-expires=1767916800&x-signature=uEjRJ6d%2BVqtVEkBNNU9PDl2A8pY%3D",
      "link": "https://www.toutiao.com/trending/7581402123875696690"
    },
    {
      "title": "巩固壮大实体经济根基",
      "hot_value": 16000221,
      "cover": "https://p3-sign.toutiaoimg.com/tos-cn-i-qvj2lq49k0/7816fd7148734efcb7b1bd57ff895e60~tplv-tt-shrink:960:540.jpeg?_iz=30575&from=sign_default&lk3s=8d617dac&x-expires=1767916800&x-signature=xbi1Xr%2F10ZoNCpl2%2F47wyt4pklM%3D",
      "link": "https://www.toutiao.com/article/7581802230509093403"
    },
    {
      "title": "乌克兰正与美欧磋商三项关键文件",
      "hot_value": 14477599,
      "cover": "https://p3-sign.toutiaoimg.com/mosaic-legacy/2b29000036f8405561443~tplv-tt-shrink:960:540.jpeg?_iz=30575&from=sign_default&lk3s=8d617dac&x-expires=1767916800&x-signature=uEjRJ6d%2BVqtVEkBNNU9PDl2A8pY%3D",
      "link": "https://www.toutiao.com/trending/7581846521767952438"
    },
    {
      "title": "学校火灾致13死 家属称被迫签协议",
      "hot_value": 13099873,
      "cover": "https://p3-sign.toutiaoimg.com/tos-cn-i-qvj2lq49k0/2ac1505f2f7544859c6844d5a2d8418b~tplv-tt-shrink:960:540.jpeg?_iz=30575&from=sign_default&lk3s=8d617dac&x-expires=1767916800&x-signature=uD28ptULjFBG7845DwG2vy2D9ZE%3D",
      "link": "https://www.toutiao.com/trending/7582063818004516362"
    },
    {
      "title": "充“劣质电”致汽车自燃？谣言",
      "hot_value": 11853255,
      "cover": "https://p3-sign.toutiaoimg.com/tos-cn-i-qvj2lq49k0/ba52da53834b4561a737e78393f07f17~tplv-tt-shrink:960:540.jpeg?_iz=30575&from=sign_default&lk3s=8d617dac&x-expires=1767916800&x-signature=8jN527o0nfqmoDsmI5sIlcmh24s%3D",
      "link": "https://www.toutiao.com/trending/7581803443355615295"
    },
    {
      "title": "日本政府加速在琉球群岛部署导弹",
      "hot_value": 10725269,
      "cover": "https://p3-sign.toutiaoimg.com/tos-cn-i-qvj2lq49k0/dac86cb4616b46d69f019b425717c53a~tplv-tt-shrink:960:540.jpeg?_iz=30575&from=sign_default&lk3s=8d617dac&x-expires=1767916800&x-signature=M60y4PP3%2ByU8ztgPbKaDbhVVI%2F4%3D",
      "link": "https://www.toutiao.com/trending/7582025938821451306"
    },
    {
      "title": "乔任梁爸爸因吃8个死蟹后住院",
      "hot_value": 9704625,
      "cover": "https://p3-sign.toutiaoimg.com/tos-cn-i-qvj2lq49k0/9bf3a1c32ee7416d9c3a17f27a4e6d61~tplv-tt-shrink:960:540.jpeg?_iz=30575&from=sign_default&lk3s=8d617dac&x-expires=1767916800&x-signature=jthBZZ6eLSpoPo5myPhLmkDKTI0%3D",
      "link": "https://www.toutiao.com/trending/7580944991095734281"
    },
    {
      "title": "睡眠不好时你会做什么",
      "hot_value": 8781107,
      "cover": "https://p3-sign.toutiaoimg.com/mosaic-legacy/2b28f000370774e5fabc5~tplv-tt-shrink:960:540.jpeg?_iz=30575&from=sign_default&lk3s=8d617dac&x-expires=1767916800&x-signature=nrpE3zgl%2BwJ8XmtvpYZESr%2Fp1M4%3D",
      "link": "https://www.toutiao.com/trending/7581713736860418075"
    },
    {
      "title": "王鸥带女儿公园游玩被偶遇",
      "hot_value": 7945474,
      "cover": "https://p3-sign.toutiaoimg.com/mosaic-legacy/2b28f000370782b583e56~tplv-tt-shrink:960:540.jpeg?_iz=30575&from=sign_default&lk3s=8d617dac&x-expires=1767916800&x-signature=Qvtv8RFfbqEVvkIashYMzyNqjs8%3D",
      "link": "https://www.toutiao.com/trending/7581760672314589193"
    },
    {
      "title": "小男孩提醒咳嗽的普京保重身体",
      "hot_value": 7189363,
      "cover": "https://p3-sign.toutiaoimg.com/mosaic-legacy/2b29000036f8405561443~tplv-tt-shrink:960:540.jpeg?_iz=30575&from=sign_default&lk3s=8d617dac&x-expires=1767916800&x-signature=uEjRJ6d%2BVqtVEkBNNU9PDl2A8pY%3D",
      "link": "https://www.toutiao.com/trending/7581505595594965046"
    },
    {
      "title": "小红书关停“最短命”项目",
      "hot_value": 6505204,
      "cover": "https://p3-sign.toutiaoimg.com/tos-cn-i-qvj2lq49k0/6c3fca4de8254c679ad2563937eefd2b~tplv-tt-shrink:960:540.jpeg?_iz=30575&from=sign_default&lk3s=8d617dac&x-expires=1767916800&x-signature=kUtL33Ws%2Bz5G0IZg5W06jeh5F4k%3D",
      "link": "https://www.toutiao.com/trending/7582035613432417838"
    },
    {
      "title": "音频实证日本有意滋扰中方训练",
      "hot_value": 5886152,
      "cover": "https://p3-sign.toutiaoimg.com/tos-cn-i-qvj2lq49k0/b18d206ec1084e528998e7b705a270c5~tplv-tt-shrink:960:540.jpeg?_iz=30575&from=sign_default&lk3s=8d617dac&x-expires=1767916800&x-signature=TLYnD0uOk%2Btl%2B0KVXoHLtQkZRZk%3D",
      "link": "https://www.toutiao.com/trending/7581049100923142153"
    },
    {
      "title": "唐驳虎：日本强震敲响警钟",
      "hot_value": 5326011,
      "cover": "https://p3-sign.toutiaoimg.com/tos-cn-i-qvj2lq49k0/ed36e3934ce34c73bf8f4a878a435787~tplv-tt-shrink:960:540.jpeg?_iz=30575&from=sign_default&lk3s=8d617dac&x-expires=1767916800&x-signature=LAiB9CXVAPSOZ8gj%2BEKtbqPW15I%3D",
      "link": "https://www.toutiao.com/trending/7581747598311034404"
    },
    {
      "title": "河南巩义一村庄流出露天温泉水",
      "hot_value": 4819174,
      "cover": "https://p3-sign.toutiaoimg.com/mosaic-legacy/2b29000036f8405561443~tplv-tt-shrink:960:540.jpeg?_iz=30575&from=sign_default&lk3s=8d617dac&x-expires=1767916800&x-signature=uEjRJ6d%2BVqtVEkBNNU9PDl2A8pY%3D",
      "link": "https://www.toutiao.com/trending/7581391482814267443"
    },
    {
      "title": "不接受高市用“立场没有变化”敷衍",
      "hot_value": 4360569,
      "cover": "https://p3-sign.toutiaoimg.com/mosaic-legacy/2b29000036f8405561443~tplv-tt-shrink:960:540.jpeg?_iz=30575&from=sign_default&lk3s=8d617dac&x-expires=1767916800&x-signature=uEjRJ6d%2BVqtVEkBNNU9PDl2A8pY%3D",
      "link": "https://www.toutiao.com/trending/7581001190985498687"
    },
    {
      "title": "孙颖莎与日本女乒开启热聊模式",
      "hot_value": 3945606,
      "cover": "https://p3-sign.toutiaoimg.com/tos-cn-i-qvj2lq49k0/f04a4849b8fc45d1bb228126f114fe54~tplv-tt-shrink:960:540.jpeg?_iz=30575&from=sign_default&lk3s=8d617dac&x-expires=1767916800&x-signature=B%2BNUIGAPQ9wAa0Uti1zS23ppB14%3D",
      "link": "https://www.toutiao.com/trending/7581490775221878790"
    },
    {
      "title": "在中国抱怨菜价贵是幸福的烦恼",
      "hot_value": 3570132,
      "cover": "https://p3-sign.toutiaoimg.com/tos-cn-i-qvj2lq49k0/62bbf895b2e94bdfb22b27bd5534ca89~tplv-tt-shrink:960:540.jpeg?_iz=30575&from=sign_default&lk3s=8d617dac&x-expires=1767916800&x-signature=6ZPC88TavVAVtmshzSkyAybOi1M%3D",
      "link": "https://www.toutiao.com/trending/7581251939090841642"
    },
    {
      "title": "西藏自治区原主席齐扎拉被公诉",
      "hot_value": 3230389,
      "cover": "https://p3-sign.toutiaoimg.com/mosaic-legacy/2b29000036f8405561443~tplv-tt-shrink:960:540.jpeg?_iz=30575&from=sign_default&lk3s=8d617dac&x-expires=1767916800&x-signature=uEjRJ6d%2BVqtVEkBNNU9PDl2A8pY%3D",
      "link": "https://www.toutiao.com/trending/7582043154742657050"
    },
    {
      "title": "美国企业界对特朗普执政表现评价不高",
      "hot_value": 2922976,
      "cover": "https://p6-sign.toutiaoimg.com/mosaic-legacy/2b29000036f8405561443~tplv-tt-shrink:960:540.jpeg?_iz=30575&from=sign_default&lk3s=8d617dac&x-expires=1767916800&x-signature=jaCmjOs%2F2YYz2TKWyPClJNUlYRI%3D",
      "link": "https://www.toutiao.com/trending/7581666417361092614"
    },
    {
      "title": "美国防部长：漠视中国军力愚蠢而失敬",
      "hot_value": 2644818,
      "cover": "https://p3-sign.toutiaoimg.com/tos-cn-i-qvj2lq49k0/3b40d544632e461d8600e020cd387c69~tplv-tt-shrink:960:540.jpeg?_iz=30575&from=sign_default&lk3s=8d617dac&x-expires=1767916800&x-signature=psrZLzNtoOmJ4ma0NJikcL9Un%2Fo%3D",
      "link": "https://www.toutiao.com/trending/7581056122527154218"
    },
    {
      "title": "美国战略大转向：承认中美对等",
      "hot_value": 2393131,
      "cover": "https://p3-sign.toutiaoimg.com/tos-cn-i-qvj2lq49k0/3340e42d6e224503a3bbbd2a70dc65c9~tplv-tt-shrink:960:540.jpeg?_iz=30575&from=sign_default&lk3s=8d617dac&x-expires=1767916800&x-signature=oy1w6NGd0V454LB3KYhAyR3iOpc%3D",
      "link": "https://www.toutiao.com/trending/7581163584785334291"
    },
    {
      "title": "鸿蒙智行新车规划一览",
      "hot_value": 2165394,
      "cover": "https://p3-sign.toutiaoimg.com/tos-cn-i-qvj2lq49k0/db8c3222da6c4735ad8de2007d88f6ee~tplv-tt-shrink:960:540.jpeg?_iz=30575&from=sign_default&lk3s=8d617dac&x-expires=1767916800&x-signature=QPJrqyxGFYf0ybcXdl96D4FmTbs%3D",
      "link": "https://www.toutiao.com/trending/7582057302476377609"
    },
    {
      "title": "特朗普称泽连斯基赚走拜登3500亿美元",
      "hot_value": 1959330,
      "cover": "https://p3-sign.toutiaoimg.com/tos-cn-i-qvj2lq49k0/c511edcc3a9c4f438372e13db170c507~tplv-tt-shrink:960:540.jpeg?_iz=30575&from=sign_default&lk3s=8d617dac&x-expires=1767916800&x-signature=YEgTsAXzEynfjJhdv60XNPNwYhM%3D",
      "link": "https://www.toutiao.com/trending/7581084674962473014"
    },
    {
      "title": "邱贻可谈孙颖莎全运摘银：输在心态",
      "hot_value": 1772875,
      "cover": "https://p3-sign.toutiaoimg.com/tos-cn-i-qvj2lq49k0/c2bb20507ffc4aaca3b2e424fc2ceeab~tplv-tt-shrink:960:540.jpeg?_iz=30575&from=sign_default&lk3s=8d617dac&x-expires=1767916800&x-signature=mf8pC1jTtA5G6GyPTyeg36IanhU%3D",
      "link": "https://www.toutiao.com/trending/7581761392550759999"
    },
    {
      "title": "余承东透露明年或将推出问界M6",
      "hot_value": 1604163,
      "cover": "https://p3-sign.toutiaoimg.com/mosaic-legacy/2b29000036f8405561443~tplv-tt-shrink:960:540.jpeg?_iz=30575&from=sign_default&lk3s=8d617dac&x-expires=1767916800&x-signature=uEjRJ6d%2BVqtVEkBNNU9PDl2A8pY%3D",
      "link": "https://www.toutiao.com/trending/7581702141497819155"
    },
    {
      "title": "中方对日斗争打出组合拳直击痛点",
      "hot_value": 1451507,
      "cover": "https://p3-sign.toutiaoimg.com/mosaic-legacy/2b28f000370774e5fabc5~tplv-tt-shrink:960:540.jpeg?_iz=30575&from=sign_default&lk3s=8d617dac&x-expires=1767916800&x-signature=nrpE3zgl%2BwJ8XmtvpYZESr%2Fp1M4%3D",
      "link": "https://www.toutiao.com/trending/7581243382811492371"
    },
    {
      "title": "特朗普再度抨击鲍威尔：他不喜欢我",
      "hot_value": 1313378,
      "cover": "https://p3-sign.toutiaoimg.com/mosaic-legacy/2b29000036f8405561443~tplv-tt-shrink:960:540.jpeg?_iz=30575&from=sign_default&lk3s=8d617dac&x-expires=1767916800&x-signature=uEjRJ6d%2BVqtVEkBNNU9PDl2A8pY%3D",
      "link": "https://www.toutiao.com/trending/7582002774414622726"
    },
    {
      "title": "日方：中俄军机联合飞行是对日本示威",
      "hot_value": 1188393,
      "cover": "https://p26-sign.toutiaoimg.com/tos-cn-i-qvj2lq49k0/9edb7a9530b04207b2aa427de46d5494~tplv-tt-shrink:960:540.jpeg?_iz=30575&from=sign_default&lk3s=8d617dac&x-expires=1767916800&x-signature=%2F4og6Avu3mm1BcYut1%2BlJTEnfBg%3D",
      "link": "https://www.toutiao.com/trending/7581790954814750747"
    },
    {
      "title": "委内瑞拉：警惕美国复辟“门罗主义”",
      "hot_value": 1075303,
      "cover": "https://p3-sign.toutiaoimg.com/mosaic-legacy/2b29000036f8405561443~tplv-tt-shrink:960:540.jpeg?_iz=30575&from=sign_default&lk3s=8d617dac&x-expires=1767916800&x-signature=uEjRJ6d%2BVqtVEkBNNU9PDl2A8pY%3D",
      "link": "https://www.toutiao.com/trending/7581609591973085227"
    },
    {
      "title": "茅台跌出近年新低 1399元触底了吗",
      "hot_value": 972974,
      "cover": "https://p3-sign.toutiaoimg.com/tos-cn-i-qvj2lq49k0/8df68c5bfacb47fabae063cfc32cb2b8~tplv-tt-shrink:960:540.jpeg?_iz=30575&from=sign_default&lk3s=8d617dac&x-expires=1767916800&x-signature=4srAqYSAGpx3a8frT6cI0RJOmrg%3D",
      "link": "https://www.toutiao.com/trending/7581467792513138707"
    },
    {
      "title": "评论员：美国进入战略收缩阶段",
      "hot_value": 880383,
      "cover": "https://p26-sign.toutiaoimg.com/tos-cn-i-qvj2lq49k0/92afca2e74554d4a8119933f56abad90~tplv-tt-shrink:960:540.jpeg?_iz=30575&from=sign_default&lk3s=8d617dac&x-expires=1767916800&x-signature=QFsyAnPeLfOtgI9IrFcmHgrhK%2B0%3D",
      "link": "https://www.toutiao.com/trending/7582022321364274742"
    },
    {
      "title": "美媒：美军两架战机飞入委领空",
      "hot_value": 796604,
      "cover": "https://p3-sign.toutiaoimg.com/mosaic-legacy/2b29000036f8405561443~tplv-tt-shrink:960:540.jpeg?_iz=30575&from=sign_default&lk3s=8d617dac&x-expires=1767916800&x-signature=uEjRJ6d%2BVqtVEkBNNU9PDl2A8pY%3D",
      "link": "https://www.toutiao.com/trending/7581798242581954601"
    },
    {
      "title": "60岁已婚男追赶35岁暧昧对象时摔死",
      "hot_value": 720797,
      "cover": "https://p3-sign.toutiaoimg.com/top-static-files-outer/breaknews/18e2fd06-d98d-4a80-b3f2-415152cf5563~tplv-tt-shrink:960:540.jpeg?_iz=30575&from=sign_default&lk3s=8d617dac&x-expires=1767916800&x-signature=XtlELk59kZ4g0m%2FDTXv6qaUqsco%3D",
      "link": "https://www.toutiao.com/trending/7581720710033178670"
    },
    {
      "title": "女子开远光被邻居闪灯提醒后破防",
      "hot_value": 652204,
      "cover": "https://p3-sign.toutiaoimg.com/mosaic-legacy/2b29000036f8405561443~tplv-tt-shrink:960:540.jpeg?_iz=30575&from=sign_default&lk3s=8d617dac&x-expires=1767916800&x-signature=uEjRJ6d%2BVqtVEkBNNU9PDl2A8pY%3D",
      "link": "https://www.toutiao.com/trending/7581496568402952235"
    },
    {
      "title": "安装工拆走客户空调关键零件",
      "hot_value": 590138,
      "cover": "https://p3-sign.toutiaoimg.com/mosaic-legacy/2b29000036f8405561443~tplv-tt-shrink:960:540.jpeg?_iz=30575&from=sign_default&lk3s=8d617dac&x-expires=1767916800&x-signature=uEjRJ6d%2BVqtVEkBNNU9PDl2A8pY%3D",
      "link": "https://www.toutiao.com/trending/7580683087202353203"
    },
    {
      "title": "中国硬核装备更高更远更有力",
      "hot_value": 533979,
      "cover": "https://p3-sign.toutiaoimg.com/tos-cn-i-qvj2lq49k0/b41b060c471445ac89997604fe769b02~tplv-tt-shrink:960:540.jpeg?_iz=30575&from=sign_default&lk3s=8d617dac&x-expires=1767916800&x-signature=MfYkjHufExx8dgluvH00s5nIDBA%3D",
      "link": "https://www.toutiao.com/trending/7581992000094945323"
    },
    {
      "title": "市民预约故宫等看雪",
      "hot_value": 483164,
      "cover": "https://p3-sign.toutiaoimg.com/tos-cn-i-qvj2lq49k0/c290f501fdad4c46978b11dd1e7c5980~tplv-tt-shrink:960:540.jpeg?_iz=30575&from=sign_default&lk3s=8d617dac&x-expires=1767916800&x-signature=M6zdDP0RyS2vw52PogfUU2DcarI%3D",
      "link": "https://www.toutiao.com/trending/7582055950790708763"
    },
    {
      "title": "立陶宛进入“国家紧急状态”",
      "hot_value": 437185,
      "cover": "https://p3-sign.toutiaoimg.com/mosaic-legacy/2b29000036f8405561443~tplv-tt-shrink:960:540.jpeg?_iz=30575&from=sign_default&lk3s=8d617dac&x-expires=1767916800&x-signature=uEjRJ6d%2BVqtVEkBNNU9PDl2A8pY%3D",
      "link": "https://www.toutiao.com/trending/7581538835981418539"
    },
    {
      "title": "智界明年将推跑车级SUV",
      "hot_value": 395581,
      "cover": "https://p26-sign.toutiaoimg.com/mosaic-legacy/2b29000036f8405561443~tplv-tt-shrink:960:540.jpeg?_iz=30575&from=sign_default&lk3s=8d617dac&x-expires=1767916800&x-signature=YuF5B9knyjxhSNsO1h9IUA278Hw%3D",
      "link": "https://www.toutiao.com/trending/7581760731440775209"
    },
    {
      "title": "媒体人：日方应停止不负责任虚假炒作",
      "hot_value": 357937,
      "cover": "https://p3-sign.toutiaoimg.com/mosaic-legacy/2b29000036f8405561443~tplv-tt-shrink:960:540.jpeg?_iz=30575&from=sign_default&lk3s=8d617dac&x-expires=1767916800&x-signature=uEjRJ6d%2BVqtVEkBNNU9PDl2A8pY%3D",
      "link": "https://www.toutiao.com/trending/7581409217292599302"
    },
    {
      "title": "用假币换真钞 两名被告人获刑",
      "hot_value": 323875,
      "cover": "https://p3-sign.toutiaoimg.com/mosaic-legacy/2b29000036f8405561443~tplv-tt-shrink:960:540.jpeg?_iz=30575&from=sign_default&lk3s=8d617dac&x-expires=1767916800&x-signature=uEjRJ6d%2BVqtVEkBNNU9PDl2A8pY%3D",
      "link": "https://www.toutiao.com/trending/7581401813767634985"
    },
    {
      "title": "俄乌冲突四方博弈如何收场",
      "hot_value": 293054,
      "cover": "https://p3-sign.toutiaoimg.com/tos-cn-i-qvj2lq49k0/926098ea061242ba8a3deca58971ca39~tplv-tt-shrink:960:540.jpeg?_iz=30575&from=sign_default&lk3s=8d617dac&x-expires=1767916800&x-signature=6x3IF9E5NpI6bBM4bSWwIQd7OH8%3D",
      "link": "https://www.toutiao.com/trending/7582038601345551899"
    },
    {
      "title": "中俄战机联合巡航哪些细节值得关注",
      "hot_value": 265166,
      "cover": "https://p3-sign.toutiaoimg.com/tos-cn-i-qvj2lq49k0/5c26e92ef5e9404e805669da8d5036c3~tplv-tt-shrink:960:540.jpeg?_iz=30575&from=sign_default&lk3s=8d617dac&x-expires=1767916800&x-signature=XzgpSKV6VtGBi0Ep8mb4fIleQ1o%3D",
      "link": "https://www.toutiao.com/trending/7582038834188127785"
    }
  ],
  "code": 200,
  "message": "获取成功，开源地址 https://github.com/vikiboss/60s，反馈群 595941841"
}