{
  "source": {
    "name": "瓦斯阅读",
    "description": "微信热门文章聚合",
    "url": "https://rss.aishort.top/?type=wasi",
    "lastUpdate": "2026-06-09T21:29:21.627Z"
  },
  "items": [
    {
      "title": "倒卖救命血，血荒催生的地下黑市",
      "link": "http://mp.weixin.qq.com/s?__biz=MzU4NDQwMDk5OQ==&amp;mid=2248144487&amp;idx=1&amp;sn=1ba0afb9898621cbc63b0b59ec9cf48e&amp;chksm=fc980d485c7414987303ed4ebea441dd6aa563e1987996f3140e3e759c6034756f2a4aad473a",
      "description": "&amp;nbsp;&amp;nbsp;&amp;nbsp;&amp;nbsp;&amp;nbsp;&amp;nbsp;&amp;nbsp;&amp;nbsp;在公众和警方的语境里，00后刘星星是个不折不扣的“恶人”。&lt;br&gt;&lt;br&gt;&amp;nbsp;&amp;nbsp;&amp;nbsp;&amp;nbsp;&amp;nbsp;&amp;nbsp;&amp;nbsp;&",
      "pubDate": "Wed, 10 Jun 2026 02:02:26 +0800",
      "timestamp": 1781028146000
    },
    {
      "title": "10年VIP，我到底错过了多少福利？",
      "link": "http://mp.weixin.qq.com/s?__biz=MjM5OTYwOTM0Nw==&amp;mid=2650558336&amp;idx=1&amp;sn=1c8aba40339cf3a0ba1e98ce6272e624&amp;chksm=bee4a0193e0546665d690b12cd337ce5d7b93c32eda29fa24be2baee42623a27a8c73fe0379f",
      "description": "&amp;nbsp;&amp;nbsp;&amp;nbsp;&amp;nbsp;&amp;nbsp;&amp;nbsp;&amp;nbsp;&amp;nbsp;酷玩实验室原创作品多年以后，面对扣费短信，我总会想起第一次成为VIP的那个遥远的晚上。&lt;br&gt;&lt;br&gt;&amp;nbsp;&amp;nbsp;&amp;nbsp;&amp;nbsp;&amp;nbsp;&amp;nb",
      "pubDate": "Wed, 10 Jun 2026 02:02:26 +0800",
      "timestamp": 1781028146000
    },
    {
      "title": "走得更远，活得更久",
      "link": "http://mp.weixin.qq.com/s?__biz=MzA3ODI5NDg0Mw==&amp;mid=2654256452&amp;idx=1&amp;sn=277f261d322538d5b5fed7dd886a2fb5&amp;chksm=855ed83db5034a71d73a4d8dfa846fde2fad3336fd89feee438f3444312a2bae93e989c72bba",
      "description": "&amp;nbsp;&amp;nbsp;&amp;nbsp;&amp;nbsp;&amp;nbsp;&amp;nbsp;&amp;nbsp;&amp;nbsp;6月初，纽约，SpaceX的IPO投资人大会上，摩根大通CEO杰米·戴蒙在纽约总部与创始人马斯克展开了一场远程对话，戴蒙把马斯克称作“我们这个时代的爱迪生”，极尽夸奖他的创造力。&lt;br&gt;&lt;br&gt;&amp;nbsp;&",
      "pubDate": "Wed, 10 Jun 2026 02:02:26 +0800",
      "timestamp": 1781028146000
    },
    {
      "title": "粉笔CEO道歉之后：年轻人需要方法，不需要羞辱",
      "link": "http://mp.weixin.qq.com/s?__biz=MzA3ODI5NDg0Mw==&amp;mid=2654256452&amp;idx=2&amp;sn=262f6085228e0995a787c42fd1a7613b&amp;chksm=851d70f0b508adefe480c45595c860f5496ceb6fc0677d16de18c0b909b2fe6160d602c6342e",
      "description": "&amp;nbsp;&amp;nbsp;&amp;nbsp;&amp;nbsp;&amp;nbsp;&amp;nbsp;&amp;nbsp;&amp;nbsp;一场高校讲座，一次言行失当，一封道歉信，为什么会引发这么大争议？&lt;br&gt;&lt;br&gt;&amp;nbsp;&amp;nbsp;&amp;nbsp;&amp;nbsp;&amp;nbsp;&amp;nbsp;&amp;nbs",
      "pubDate": "Wed, 10 Jun 2026 02:02:26 +0800",
      "timestamp": 1781028146000
    },
    {
      "title": "金融行业，无砖可搬？",
      "link": "http://mp.weixin.qq.com/s?__biz=Mzg5NTI0NjU3NQ==&amp;mid=2247497457&amp;idx=1&amp;sn=2c84f873c8c2104acd454f2afc83cee8&amp;chksm=c1c1efe7459199476034fbaa5da645391bc9828ddc82ff12c45e808f4787b83e229c7a0d0799",
      "description": "&amp;nbsp;&amp;nbsp;&amp;nbsp;&amp;nbsp;&amp;nbsp;&amp;nbsp;&amp;nbsp;&amp;nbsp;作者｜Hayward原创首发｜蓝字计划金融圈有个传了三十年的笑话：招最聪明的名校生，干最没技术含量的Excel文档整理活。&lt;br&gt;&lt;br&gt;&amp;nbsp;&amp;nbsp;&amp;nbsp;&amp;nbsp",
      "pubDate": "Wed, 10 Jun 2026 00:02:28 +0800",
      "timestamp": 1781020948000
    },
    {
      "title": "华夏良子IPO前夜：董事长持股99.9%，强制办卡频发，曾与爱奇艺对簿公堂",
      "link": "http://mp.weixin.qq.com/s?__biz=MzA4NTc3MDYyOQ==&amp;mid=2651589430&amp;idx=3&amp;sn=59b9554ccdee08943c55cf1c7d06a203&amp;chksm=855bbccb4d16e67c30a4d0345814f7596cf552860933059a043c4a3cbad9e6a207201a974f3b",
      "description": "&amp;nbsp;&amp;nbsp;&amp;nbsp;&amp;nbsp;&amp;nbsp;&amp;nbsp;&amp;nbsp;&amp;nbsp;文 | 《BUG》栏目 徐苑蕾一场签约仪式，让国人“脚底板”上最熟悉的企业，悄然站到了港交所的门前。&lt;br&gt;&lt;br&gt;&amp;nbsp;&amp;nbsp;&amp;nbsp;&amp;nbsp;&amp;nbsp;",
      "pubDate": "Wed, 10 Jun 2026 00:02:28 +0800",
      "timestamp": 1781020948000
    },
    {
      "title": "苹果把Siri交给了Gemini",
      "link": "http://mp.weixin.qq.com/s?__biz=Mzk0MDYyMDA0NQ==&amp;mid=2247492786&amp;idx=1&amp;sn=a10c4ba9063c0a1f05a675dac2be1f8d&amp;chksm=c3b4031318bb6b44ce3d7a2e11f87f4c8fefab01b35e2608a14e1f5712ea6e6efd77c09b94f3",
      "description": "&amp;nbsp;&amp;nbsp;&amp;nbsp;&amp;nbsp;&amp;nbsp;&amp;nbsp;&amp;nbsp;&amp;nbsp;文丨邱庭编辑丨程述白2011年10月4日，蒂姆·库克（Tim Cook）第一次以苹果CEO身份主持发布会——&lt;br&gt;&lt;br&gt;&amp;nbsp;&amp;nbsp;&amp;nbsp;&amp;nbsp;&amp;n",
      "pubDate": "Wed, 10 Jun 2026 00:02:28 +0800",
      "timestamp": 1781020948000
    },
    {
      "title": "7天内，天津银行两度挨罚",
      "link": "http://mp.weixin.qq.com/s?__biz=MzI4OTcxMDA0MQ==&amp;mid=2247546352&amp;idx=1&amp;sn=0790fe94b8358eef1ff9a32d4b9c4c0e&amp;chksm=ed545ea203046a31402c37c724c72546196fabafa7bcf76d96d69204afbdd4829df5ae1aa31c",
      "description": "&amp;nbsp;&amp;nbsp;&amp;nbsp;&amp;nbsp;&amp;nbsp;&amp;nbsp;&amp;nbsp;&amp;nbsp;7天之内，天津银行接连领了两次罚单。近日，天津银行因重要信息系统对外服务异常事件应报未报，被罚款20万元。&lt;br&gt;&lt;br&gt;&amp;nbsp;&amp;nbsp;&amp;nbsp;&amp;nbsp;&amp;nb",
      "pubDate": "Wed, 10 Jun 2026 00:02:28 +0800",
      "timestamp": 1781020948000
    },
    {
      "title": "集成电路第二城，不想再“隐形”",
      "link": "http://mp.weixin.qq.com/s?__biz=Mzg2MjA5Mjc0OA==&amp;mid=2247580670&amp;idx=1&amp;sn=090acab44dd8255477f65e09fb7105dc&amp;chksm=cf015d05470bf10f8512c6d0bfa91b6839c6443bccbb585d9ff74d73cf0af836d87769f8f033",
      "description": "&amp;nbsp;&amp;nbsp;&amp;nbsp;&amp;nbsp;&amp;nbsp;&amp;nbsp;&amp;nbsp;&amp;nbsp;迈向“2万亿”，无锡打响守位战近日，一场聚焦集成电路产业的专题推进会在无锡召开。&lt;br&gt;&lt;br&gt;&amp;nbsp;&amp;nbsp;&amp;nbsp;&amp;nbsp;&amp;nbsp;&amp;nbsp;",
      "pubDate": "Wed, 10 Jun 2026 00:02:28 +0800",
      "timestamp": 1781020948000
    },
    {
      "title": "卷完训练卷恢复，「运动营养」是都市青年的第二战场",
      "link": "http://mp.weixin.qq.com/s?__biz=MzU1NjYyMjI1Nw==&amp;mid=2247591826&amp;idx=1&amp;sn=a67e100a67d2ab1d19160418772052a8&amp;chksm=faa23cbf2a396e94c2cc263322252db78bb2a81fa6b387c6145d7f315e0372359ff56f33fd2f",
      "description": "&amp;nbsp;&amp;nbsp;&amp;nbsp;&amp;nbsp;&amp;nbsp;&amp;nbsp;&amp;nbsp;&amp;nbsp;在健身房卷力量，离开健身房卷营养，「运动后吃什么，如何补充更有效」成为当下都市健身人的练后新议题。&lt;br&gt;&lt;br&gt;&amp;nbsp;&amp;nbsp;&amp;nbsp;&amp;nbsp;&amp;nbsp;&",
      "pubDate": "Wed, 10 Jun 2026 00:02:28 +0800",
      "timestamp": 1781020948000
    }
  ],
  "total": 10
}