{
  "source": {
    "name": "微博热榜",
    "description": "微博热搜榜",
    "url": "https://60s.viki.moe/v2/weibo",
    "lastUpdate": "2026-03-27T01:19:07.787Z"
  },
  "data": [
    {
      "title": "罗技就侮辱性广告致歉",
      "hot_value": 1238031,
      "link": "https://s.weibo.com/weibo?q=%E7%BD%97%E6%8A%80%E5%B0%B1%E4%BE%AE%E8%BE%B1%E6%80%A7%E5%B9%BF%E5%91%8A%E8%87%B4%E6%AD%89"
    },
    {
      "title": "8岁被领养至加拿大又遭遗弃",
      "hot_value": 896848,
      "link": "https://s.weibo.com/weibo?q=8%E5%B2%81%E8%A2%AB%E9%A2%86%E5%85%BB%E8%87%B3%E5%8A%A0%E6%8B%BF%E5%A4%A7%E5%8F%88%E9%81%AD%E9%81%97%E5%BC%83"
    },
    {
      "title": "2026中国网络媒体论坛",
      "hot_value": 715975,
      "link": "https://s.weibo.com/weibo?q=2026%E4%B8%AD%E5%9B%BD%E7%BD%91%E7%BB%9C%E5%AA%92%E4%BD%93%E8%AE%BA%E5%9D%9B"
    },
    {
      "title": "食贫道谈日本女性养牛郎现象",
      "hot_value": 581241,
      "link": "https://s.weibo.com/weibo?q=%E9%A3%9F%E8%B4%AB%E9%81%93%E8%B0%88%E6%97%A5%E6%9C%AC%E5%A5%B3%E6%80%A7%E5%85%BB%E7%89%9B%E9%83%8E%E7%8E%B0%E8%B1%A1"
    },
    {
      "title": "伊朗正式回应美国15点停火协议",
      "hot_value": 417608,
      "link": "https://s.weibo.com/weibo?q=%E4%BC%8A%E6%9C%97%E6%AD%A3%E5%BC%8F%E5%9B%9E%E5%BA%94%E7%BE%8E%E5%9B%BD15%E7%82%B9%E5%81%9C%E7%81%AB%E5%8D%8F%E8%AE%AE"
    },
    {
      "title": "央视新闻夸了张凌赫雉鸡翎造型",
      "hot_value": 332852,
      "link": "https://s.weibo.com/weibo?q=%E5%A4%AE%E8%A7%86%E6%96%B0%E9%97%BB%E5%A4%B8%E4%BA%86%E5%BC%A0%E5%87%8C%E8%B5%AB%E9%9B%89%E9%B8%A1%E7%BF%8E%E9%80%A0%E5%9E%8B"
    },
    {
      "title": "女子因停车争吵身亡家属索赔122万",
      "hot_value": 287815,
      "link": "https://s.weibo.com/weibo?q=%E5%A5%B3%E5%AD%90%E5%9B%A0%E5%81%9C%E8%BD%A6%E4%BA%89%E5%90%B5%E8%BA%AB%E4%BA%A1%E5%AE%B6%E5%B1%9E%E7%B4%A2%E8%B5%94122%E4%B8%87"
    },
    {
      "title": "李昀锐孟子义撕名牌路透",
      "hot_value": 219602,
      "link": "https://s.weibo.com/weibo?q=%E6%9D%8E%E6%98%80%E9%94%90%E5%AD%9F%E5%AD%90%E4%B9%89%E6%92%95%E5%90%8D%E7%89%8C%E8%B7%AF%E9%80%8F"
    },
    {
      "title": "特朗普称对伊能源空袭再推迟10天",
      "hot_value": 212088,
      "link": "https://s.weibo.com/weibo?q=%E7%89%B9%E6%9C%97%E6%99%AE%E7%A7%B0%E5%AF%B9%E4%BC%8A%E8%83%BD%E6%BA%90%E7%A9%BA%E8%A2%AD%E5%86%8D%E6%8E%A8%E8%BF%9F10%E5%A4%A9"
    },
    {
      "title": "小孩哥淘到疑似日军细菌战账单",
      "hot_value": 190556,
      "link": "https://s.weibo.com/weibo?q=%E5%B0%8F%E5%AD%A9%E5%93%A5%E6%B7%98%E5%88%B0%E7%96%91%E4%BC%BC%E6%97%A5%E5%86%9B%E7%BB%86%E8%8F%8C%E6%88%98%E8%B4%A6%E5%8D%95"
    },
    {
      "title": "没认出来这是王子异",
      "hot_value": 190331,
      "link": "https://s.weibo.com/weibo?q=%E6%B2%A1%E8%AE%A4%E5%87%BA%E6%9D%A5%E8%BF%99%E6%98%AF%E7%8E%8B%E5%AD%90%E5%BC%82"
    },
    {
      "title": "国产伟哥2025年少卖近800万片",
      "hot_value": 189849,
      "link": "https://s.weibo.com/weibo?q=%E5%9B%BD%E4%BA%A7%E4%BC%9F%E5%93%A52025%E5%B9%B4%E5%B0%91%E5%8D%96%E8%BF%91800%E4%B8%87%E7%89%87"
    },
    {
      "title": "人民的名义演员被诉休庭未宣判",
      "hot_value": 189634,
      "link": "https://s.weibo.com/weibo?q=%E4%BA%BA%E6%B0%91%E7%9A%84%E5%90%8D%E4%B9%89%E6%BC%94%E5%91%98%E8%A2%AB%E8%AF%89%E4%BC%91%E5%BA%AD%E6%9C%AA%E5%AE%A3%E5%88%A4"
    },
    {
      "title": "白鹿录完跑男状态",
      "hot_value": 189193,
      "link": "https://s.weibo.com/weibo?q=%E7%99%BD%E9%B9%BF%E5%BD%95%E5%AE%8C%E8%B7%91%E7%94%B7%E7%8A%B6%E6%80%81"
    },
    {
      "title": "全国猪价已跌破5元",
      "hot_value": 189136,
      "link": "https://s.weibo.com/weibo?q=%E5%85%A8%E5%9B%BD%E7%8C%AA%E4%BB%B7%E5%B7%B2%E8%B7%8C%E7%A0%B45%E5%85%83"
    },
    {
      "title": "张凌赫回应最近好瘦",
      "hot_value": 180942,
      "link": "https://s.weibo.com/weibo?q=%E5%BC%A0%E5%87%8C%E8%B5%AB%E5%9B%9E%E5%BA%94%E6%9C%80%E8%BF%91%E5%A5%BD%E7%98%A6"
    },
    {
      "title": "逐玉谢征吸长玉锁骨",
      "hot_value": 174163,
      "link": "https://s.weibo.com/weibo?q=%E9%80%90%E7%8E%89%E8%B0%A2%E5%BE%81%E5%90%B8%E9%95%BF%E7%8E%89%E9%94%81%E9%AA%A8"
    },
    {
      "title": "为什么房间里那么多灰尘毛",
      "hot_value": 152790,
      "link": "https://s.weibo.com/weibo?q=%E4%B8%BA%E4%BB%80%E4%B9%88%E6%88%BF%E9%97%B4%E9%87%8C%E9%82%A3%E4%B9%88%E5%A4%9A%E7%81%B0%E5%B0%98%E6%AF%9B"
    },
    {
      "title": "杨笠的脑子转得太快了",
      "hot_value": 152555,
      "link": "https://s.weibo.com/weibo?q=%E6%9D%A8%E7%AC%A0%E7%9A%84%E8%84%91%E5%AD%90%E8%BD%AC%E5%BE%97%E5%A4%AA%E5%BF%AB%E4%BA%86"
    },
    {
      "title": "Crisp怒喷Kanavi",
      "hot_value": 150442,
      "link": "https://s.weibo.com/weibo?q=Crisp%E6%80%92%E5%96%B7Kanavi"
    },
    {
      "title": "南方将有暴雨大暴雨",
      "hot_value": 149163,
      "link": "https://s.weibo.com/weibo?q=%E5%8D%97%E6%96%B9%E5%B0%86%E6%9C%89%E6%9A%B4%E9%9B%A8%E5%A4%A7%E6%9A%B4%E9%9B%A8"
    },
    {
      "title": "伊总统称伊朗致力于全面结束战争",
      "hot_value": 142333,
      "link": "https://s.weibo.com/weibo?q=%E4%BC%8A%E6%80%BB%E7%BB%9F%E7%A7%B0%E4%BC%8A%E6%9C%97%E8%87%B4%E5%8A%9B%E4%BA%8E%E5%85%A8%E9%9D%A2%E7%BB%93%E6%9D%9F%E6%88%98%E4%BA%89"
    },
    {
      "title": "存储芯片板块暴跌原因",
      "hot_value": 128656,
      "link": "https://s.weibo.com/weibo?q=%E5%AD%98%E5%82%A8%E8%8A%AF%E7%89%87%E6%9D%BF%E5%9D%97%E6%9A%B4%E8%B7%8C%E5%8E%9F%E5%9B%A0"
    },
    {
      "title": "医院回应女婴刚出生一天没有肛门",
      "hot_value": 124933,
      "link": "https://s.weibo.com/weibo?q=%E5%8C%BB%E9%99%A2%E5%9B%9E%E5%BA%94%E5%A5%B3%E5%A9%B4%E5%88%9A%E5%87%BA%E7%94%9F%E4%B8%80%E5%A4%A9%E6%B2%A1%E6%9C%89%E8%82%9B%E9%97%A8"
    },
    {
      "title": "罗技侮辱消费者",
      "hot_value": 124838,
      "link": "https://s.weibo.com/weibo?q=%E7%BD%97%E6%8A%80%E4%BE%AE%E8%BE%B1%E6%B6%88%E8%B4%B9%E8%80%85"
    },
    {
      "title": "马杜罗夫妇关押地如同人间炼狱",
      "hot_value": 122835,
      "link": "https://s.weibo.com/weibo?q=%E9%A9%AC%E6%9D%9C%E7%BD%97%E5%A4%AB%E5%A6%87%E5%85%B3%E6%8A%BC%E5%9C%B0%E5%A6%82%E5%90%8C%E4%BA%BA%E9%97%B4%E7%82%BC%E7%8B%B1"
    },
    {
      "title": "谢征樊长玉被窝戏删掉了",
      "hot_value": 111800,
      "link": "https://s.weibo.com/weibo?q=%E8%B0%A2%E5%BE%81%E6%A8%8A%E9%95%BF%E7%8E%89%E8%A2%AB%E7%AA%9D%E6%88%8F%E5%88%A0%E6%8E%89%E4%BA%86"
    },
    {
      "title": "白敬亭郑合惠子互动",
      "hot_value": 98033,
      "link": "https://s.weibo.com/weibo?q=%E7%99%BD%E6%95%AC%E4%BA%AD%E9%83%91%E5%90%88%E6%83%A0%E5%AD%90%E4%BA%92%E5%8A%A8"
    },
    {
      "title": "女生相亲被带去摸鱼收获铁锅炖",
      "hot_value": 95208,
      "link": "https://s.weibo.com/weibo?q=%E5%A5%B3%E7%94%9F%E7%9B%B8%E4%BA%B2%E8%A2%AB%E5%B8%A6%E5%8E%BB%E6%91%B8%E9%B1%BC%E6%94%B6%E8%8E%B7%E9%93%81%E9%94%85%E7%82%96"
    },
    {
      "title": "逐玉原著这段无法保持苹果肌扁平",
      "hot_value": 94941,
      "link": "https://s.weibo.com/weibo?q=%E9%80%90%E7%8E%89%E5%8E%9F%E8%91%97%E8%BF%99%E6%AE%B5%E6%97%A0%E6%B3%95%E4%BF%9D%E6%8C%81%E8%8B%B9%E6%9E%9C%E8%82%8C%E6%89%81%E5%B9%B3"
    },
    {
      "title": "日本东京发生命案",
      "hot_value": 94226,
      "link": "https://s.weibo.com/weibo?q=%E6%97%A5%E6%9C%AC%E4%B8%9C%E4%BA%AC%E5%8F%91%E7%94%9F%E5%91%BD%E6%A1%88"
    },
    {
      "title": "日本6.4级地震",
      "hot_value": 92817,
      "link": "https://s.weibo.com/weibo?q=%E6%97%A5%E6%9C%AC6.4%E7%BA%A7%E5%9C%B0%E9%9C%87"
    },
    {
      "title": "医生称医院心内科挤满跑友",
      "hot_value": 92125,
      "link": "https://s.weibo.com/weibo?q=%E5%8C%BB%E7%94%9F%E7%A7%B0%E5%8C%BB%E9%99%A2%E5%BF%83%E5%86%85%E7%A7%91%E6%8C%A4%E6%BB%A1%E8%B7%91%E5%8F%8B"
    },
    {
      "title": "日舰在美完成改装可发射战斧",
      "hot_value": 91887,
      "link": "https://s.weibo.com/weibo?q=%E6%97%A5%E8%88%B0%E5%9C%A8%E7%BE%8E%E5%AE%8C%E6%88%90%E6%94%B9%E8%A3%85%E5%8F%AF%E5%8F%91%E5%B0%84%E6%88%98%E6%96%A7"
    },
    {
      "title": "黄金又开始拉扯",
      "hot_value": 91850,
      "link": "https://s.weibo.com/weibo?q=%E9%BB%84%E9%87%91%E5%8F%88%E5%BC%80%E5%A7%8B%E6%8B%89%E6%89%AF"
    },
    {
      "title": "孟子义李昀锐装不熟",
      "hot_value": 91827,
      "link": "https://s.weibo.com/weibo?q=%E5%AD%9F%E5%AD%90%E4%B9%89%E6%9D%8E%E6%98%80%E9%94%90%E8%A3%85%E4%B8%8D%E7%86%9F"
    },
    {
      "title": "中国移动日赚3.76亿",
      "hot_value": 87912,
      "link": "https://s.weibo.com/weibo?q=%E4%B8%AD%E5%9B%BD%E7%A7%BB%E5%8A%A8%E6%97%A5%E8%B5%9A3.76%E4%BA%BF"
    },
    {
      "title": "苹果罕见重金奖励iPhone设计团队",
      "hot_value": 77656,
      "link": "https://s.weibo.com/weibo?q=%E8%8B%B9%E6%9E%9C%E7%BD%95%E8%A7%81%E9%87%8D%E9%87%91%E5%A5%96%E5%8A%B1iPhone%E8%AE%BE%E8%AE%A1%E5%9B%A2%E9%98%9F"
    },
    {
      "title": "林俊杰称自己生命的沙漏加速了",
      "hot_value": 75041,
      "link": "https://s.weibo.com/weibo?q=%E6%9E%97%E4%BF%8A%E6%9D%B0%E7%A7%B0%E8%87%AA%E5%B7%B1%E7%94%9F%E5%91%BD%E7%9A%84%E6%B2%99%E6%BC%8F%E5%8A%A0%E9%80%9F%E4%BA%86"
    },
    {
      "title": "G2爆料训练赛战绩",
      "hot_value": 74640,
      "link": "https://s.weibo.com/weibo?q=G2%E7%88%86%E6%96%99%E8%AE%AD%E7%BB%83%E8%B5%9B%E6%88%98%E7%BB%A9"
    },
    {
      "title": "罗技称已处理相关涉事人员",
      "hot_value": 74600,
      "link": "https://s.weibo.com/weibo?q=%E7%BD%97%E6%8A%80%E7%A7%B0%E5%B7%B2%E5%A4%84%E7%90%86%E7%9B%B8%E5%85%B3%E6%B6%89%E4%BA%8B%E4%BA%BA%E5%91%98"
    },
    {
      "title": "瑞银看涨金价至5900美元",
      "hot_value": 73657,
      "link": "https://s.weibo.com/weibo?q=%E7%91%9E%E9%93%B6%E7%9C%8B%E6%B6%A8%E9%87%91%E4%BB%B7%E8%87%B35900%E7%BE%8E%E5%85%83"
    },
    {
      "title": "陈飞宇迪丽热巴两集短剧",
      "hot_value": 73018,
      "link": "https://s.weibo.com/weibo?q=%E9%99%88%E9%A3%9E%E5%AE%87%E8%BF%AA%E4%B8%BD%E7%83%AD%E5%B7%B4%E4%B8%A4%E9%9B%86%E7%9F%AD%E5%89%A7"
    },
    {
      "title": "这样的民族败类必将被钉在历史耻辱柱上",
      "hot_value": 71968,
      "link": "https://s.weibo.com/weibo?q=%E8%BF%99%E6%A0%B7%E7%9A%84%E6%B0%91%E6%97%8F%E8%B4%A5%E7%B1%BB%E5%BF%85%E5%B0%86%E8%A2%AB%E9%92%89%E5%9C%A8%E5%8E%86%E5%8F%B2%E8%80%BB%E8%BE%B1%E6%9F%B1%E4%B8%8A"
    },
    {
      "title": "万万没想到一碗烩面后劲这么大",
      "hot_value": 70384,
      "link": "https://s.weibo.com/weibo?q=%E4%B8%87%E4%B8%87%E6%B2%A1%E6%83%B3%E5%88%B0%E4%B8%80%E7%A2%97%E7%83%A9%E9%9D%A2%E5%90%8E%E5%8A%B2%E8%BF%99%E4%B9%88%E5%A4%A7"
    },
    {
      "title": "男子出差回来得知花36元中995万",
      "hot_value": 70248,
      "link": "https://s.weibo.com/weibo?q=%E7%94%B7%E5%AD%90%E5%87%BA%E5%B7%AE%E5%9B%9E%E6%9D%A5%E5%BE%97%E7%9F%A5%E8%8A%B136%E5%85%83%E4%B8%AD995%E4%B8%87"
    },
    {
      "title": "4个方法降低熬夜伤害",
      "hot_value": 69288,
      "link": "https://s.weibo.com/weibo?q=4%E4%B8%AA%E6%96%B9%E6%B3%95%E9%99%8D%E4%BD%8E%E7%86%AC%E5%A4%9C%E4%BC%A4%E5%AE%B3"
    },
    {
      "title": "王曼昱入选山东鲁能名人堂",
      "hot_value": 65678,
      "link": "https://s.weibo.com/weibo?q=%E7%8E%8B%E6%9B%BC%E6%98%B1%E5%85%A5%E9%80%89%E5%B1%B1%E4%B8%9C%E9%B2%81%E8%83%BD%E5%90%8D%E4%BA%BA%E5%A0%82"
    },
    {
      "title": "美股创近1个月最大单日跌幅",
      "hot_value": 65159,
      "link": "https://s.weibo.com/weibo?q=%E7%BE%8E%E8%82%A1%E5%88%9B%E8%BF%911%E4%B8%AA%E6%9C%88%E6%9C%80%E5%A4%A7%E5%8D%95%E6%97%A5%E8%B7%8C%E5%B9%85"
    },
    {
      "title": "韩国垃圾袋一袋难求",
      "hot_value": 63215,
      "link": "https://s.weibo.com/weibo?q=%E9%9F%A9%E5%9B%BD%E5%9E%83%E5%9C%BE%E8%A2%8B%E4%B8%80%E8%A2%8B%E9%9A%BE%E6%B1%82"
    }
  ],
  "code": 200,
  "message": "获取成功，开源地址 https://github.com/vikiboss/60s，反馈群 595941841"
}