{
  "source": {
    "name": "微博热榜",
    "description": "微博热搜榜",
    "url": "https://60s.viki.moe/v2/weibo",
    "lastUpdate": "2026-07-03T01:53:56.462Z"
  },
  "data": [
    {
      "title": "葡萄牙vs克罗地亚",
      "hot_value": 12157239,
      "link": "https://s.weibo.com/weibo?q=%E8%91%A1%E8%90%84%E7%89%99vs%E5%85%8B%E7%BD%97%E5%9C%B0%E4%BA%9A"
    },
    {
      "title": "克罗地亚绝平球被吹",
      "hot_value": 3485509,
      "link": "https://s.weibo.com/weibo?q=%E5%85%8B%E7%BD%97%E5%9C%B0%E4%BA%9A%E7%BB%9D%E5%B9%B3%E7%90%83%E8%A2%AB%E5%90%B9"
    },
    {
      "title": "中国共产党人的初心",
      "hot_value": 2002093,
      "link": "https://s.weibo.com/weibo?q=%E4%B8%AD%E5%9B%BD%E5%85%B1%E4%BA%A7%E5%85%9A%E4%BA%BA%E7%9A%84%E5%88%9D%E5%BF%83"
    },
    {
      "title": "经脉受损心气散了",
      "hot_value": 1884434,
      "link": "https://s.weibo.com/weibo?q=%E7%BB%8F%E8%84%89%E5%8F%97%E6%8D%9F%E5%BF%83%E6%B0%94%E6%95%A3%E4%BA%86"
    },
    {
      "title": "葡萄牙克罗地亚裁判",
      "hot_value": 1641001,
      "link": "https://s.weibo.com/weibo?q=%E8%91%A1%E8%90%84%E7%89%99%E5%85%8B%E7%BD%97%E5%9C%B0%E4%BA%9A%E8%A3%81%E5%88%A4"
    },
    {
      "title": "C罗点球破门",
      "hot_value": 1608361,
      "link": "https://s.weibo.com/weibo?q=C%E7%BD%97%E7%82%B9%E7%90%83%E7%A0%B4%E9%97%A8"
    },
    {
      "title": "网传白鹿出演李清照",
      "hot_value": 1457614,
      "link": "https://s.weibo.com/weibo?q=%E7%BD%91%E4%BC%A0%E7%99%BD%E9%B9%BF%E5%87%BA%E6%BC%94%E6%9D%8E%E6%B8%85%E7%85%A7"
    },
    {
      "title": "鸿蒙因不兼容多CPU架构落选",
      "hot_value": 415020,
      "link": "https://s.weibo.com/weibo?q=%E9%B8%BF%E8%92%99%E5%9B%A0%E4%B8%8D%E5%85%BC%E5%AE%B9%E5%A4%9ACPU%E6%9E%B6%E6%9E%84%E8%90%BD%E9%80%89"
    },
    {
      "title": "丁禹兮宋祖儿戏外路透",
      "hot_value": 367051,
      "link": "https://s.weibo.com/weibo?q=%E4%B8%81%E7%A6%B9%E5%85%AE%E5%AE%8B%E7%A5%96%E5%84%BF%E6%88%8F%E5%A4%96%E8%B7%AF%E9%80%8F"
    },
    {
      "title": "赛格商场坠楼男子生前好友发声",
      "hot_value": 365438,
      "link": "https://s.weibo.com/weibo?q=%E8%B5%9B%E6%A0%BC%E5%95%86%E5%9C%BA%E5%9D%A0%E6%A5%BC%E7%94%B7%E5%AD%90%E7%94%9F%E5%89%8D%E5%A5%BD%E5%8F%8B%E5%8F%91%E5%A3%B0"
    },
    {
      "title": "C罗魔笛紧紧相拥",
      "hot_value": 364252,
      "link": "https://s.weibo.com/weibo?q=C%E7%BD%97%E9%AD%94%E7%AC%9B%E7%B4%A7%E7%B4%A7%E7%9B%B8%E6%8B%A5"
    },
    {
      "title": "金价暴力拉涨",
      "hot_value": 363252,
      "link": "https://s.weibo.com/weibo?q=%E9%87%91%E4%BB%B7%E6%9A%B4%E5%8A%9B%E6%8B%89%E6%B6%A8"
    },
    {
      "title": "葡萄牙2比1克罗地亚",
      "hot_value": 360387,
      "link": "https://s.weibo.com/weibo?q=%E8%91%A1%E8%90%84%E7%89%992%E6%AF%941%E5%85%8B%E7%BD%97%E5%9C%B0%E4%BA%9A"
    },
    {
      "title": "克罗地亚三粒进球被吹越位",
      "hot_value": 358763,
      "link": "https://s.weibo.com/weibo?q=%E5%85%8B%E7%BD%97%E5%9C%B0%E4%BA%9A%E4%B8%89%E7%B2%92%E8%BF%9B%E7%90%83%E8%A2%AB%E5%90%B9%E8%B6%8A%E4%BD%8D"
    },
    {
      "title": "茉莉奶白换彩色头像",
      "hot_value": 356857,
      "link": "https://s.weibo.com/weibo?q=%E8%8C%89%E8%8E%89%E5%A5%B6%E7%99%BD%E6%8D%A2%E5%BD%A9%E8%89%B2%E5%A4%B4%E5%83%8F"
    },
    {
      "title": "黄子韬留在海关的颜值回来了",
      "hot_value": 355599,
      "link": "https://s.weibo.com/weibo?q=%E9%BB%84%E5%AD%90%E9%9F%AC%E7%95%99%E5%9C%A8%E6%B5%B7%E5%85%B3%E7%9A%84%E9%A2%9C%E5%80%BC%E5%9B%9E%E6%9D%A5%E4%BA%86"
    },
    {
      "title": "C罗进球越位被吹",
      "hot_value": 354966,
      "link": "https://s.weibo.com/weibo?q=C%E7%BD%97%E8%BF%9B%E7%90%83%E8%B6%8A%E4%BD%8D%E8%A2%AB%E5%90%B9"
    },
    {
      "title": "我讨好领导就白敬亭这样",
      "hot_value": 352662,
      "link": "https://s.weibo.com/weibo?q=%E6%88%91%E8%AE%A8%E5%A5%BD%E9%A2%86%E5%AF%BC%E5%B0%B1%E7%99%BD%E6%95%AC%E4%BA%AD%E8%BF%99%E6%A0%B7"
    },
    {
      "title": "高市早苗访问印度",
      "hot_value": 351272,
      "link": "https://s.weibo.com/weibo?q=%E9%AB%98%E5%B8%82%E6%97%A9%E8%8B%97%E8%AE%BF%E9%97%AE%E5%8D%B0%E5%BA%A6"
    },
    {
      "title": "C罗哭了",
      "hot_value": 348767,
      "link": "https://s.weibo.com/weibo?q=C%E7%BD%97%E5%93%AD%E4%BA%86"
    },
    {
      "title": "突然发现普通家庭没教社会化",
      "hot_value": 346782,
      "link": "https://s.weibo.com/weibo?q=%E7%AA%81%E7%84%B6%E5%8F%91%E7%8E%B0%E6%99%AE%E9%80%9A%E5%AE%B6%E5%BA%AD%E6%B2%A1%E6%95%99%E7%A4%BE%E4%BC%9A%E5%8C%96"
    },
    {
      "title": "虞书欣连体衣",
      "hot_value": 346264,
      "link": "https://s.weibo.com/weibo?q=%E8%99%9E%E4%B9%A6%E6%AC%A3%E8%BF%9E%E4%BD%93%E8%A1%A3"
    },
    {
      "title": "肖战一直在安抚薛洋替身演员",
      "hot_value": 344317,
      "link": "https://s.weibo.com/weibo?q=%E8%82%96%E6%88%98%E4%B8%80%E7%9B%B4%E5%9C%A8%E5%AE%89%E6%8A%9A%E8%96%9B%E6%B4%8B%E6%9B%BF%E8%BA%AB%E6%BC%94%E5%91%98"
    },
    {
      "title": "微博访客记录",
      "hot_value": 343082,
      "link": "https://s.weibo.com/weibo?q=%E5%BE%AE%E5%8D%9A%E8%AE%BF%E5%AE%A2%E8%AE%B0%E5%BD%95"
    },
    {
      "title": "大热W姓男星屈指可数",
      "hot_value": 340920,
      "link": "https://s.weibo.com/weibo?q=%E5%A4%A7%E7%83%ADW%E5%A7%93%E7%94%B7%E6%98%9F%E5%B1%88%E6%8C%87%E5%8F%AF%E6%95%B0"
    },
    {
      "title": "杨紫全方位爆发",
      "hot_value": 339562,
      "link": "https://s.weibo.com/weibo?q=%E6%9D%A8%E7%B4%AB%E5%85%A8%E6%96%B9%E4%BD%8D%E7%88%86%E5%8F%91"
    },
    {
      "title": "C罗进球就越位一点点",
      "hot_value": 337782,
      "link": "https://s.weibo.com/weibo?q=C%E7%BD%97%E8%BF%9B%E7%90%83%E5%B0%B1%E8%B6%8A%E4%BD%8D%E4%B8%80%E7%82%B9%E7%82%B9"
    },
    {
      "title": "肖战曾被薛洋替身刺破嘴唇",
      "hot_value": 335798,
      "link": "https://s.weibo.com/weibo?q=%E8%82%96%E6%88%98%E6%9B%BE%E8%A2%AB%E8%96%9B%E6%B4%8B%E6%9B%BF%E8%BA%AB%E5%88%BA%E7%A0%B4%E5%98%B4%E5%94%87"
    },
    {
      "title": "虞书欣侯明昊念相思同框",
      "hot_value": 333923,
      "link": "https://s.weibo.com/weibo?q=%E8%99%9E%E4%B9%A6%E6%AC%A3%E4%BE%AF%E6%98%8E%E6%98%8A%E5%BF%B5%E7%9B%B8%E6%80%9D%E5%90%8C%E6%A1%86"
    },
    {
      "title": "韩国博主在日本整治撞人族",
      "hot_value": 331821,
      "link": "https://s.weibo.com/weibo?q=%E9%9F%A9%E5%9B%BD%E5%8D%9A%E4%B8%BB%E5%9C%A8%E6%97%A5%E6%9C%AC%E6%95%B4%E6%B2%BB%E6%92%9E%E4%BA%BA%E6%97%8F"
    },
    {
      "title": "白鹿30天掉粉117万",
      "hot_value": 330731,
      "link": "https://s.weibo.com/weibo?q=%E7%99%BD%E9%B9%BF30%E5%A4%A9%E6%8E%89%E7%B2%89117%E4%B8%87"
    },
    {
      "title": "九寨沟一男子被挤下步道落入钙化池",
      "hot_value": 328299,
      "link": "https://s.weibo.com/weibo?q=%E4%B9%9D%E5%AF%A8%E6%B2%9F%E4%B8%80%E7%94%B7%E5%AD%90%E8%A2%AB%E6%8C%A4%E4%B8%8B%E6%AD%A5%E9%81%93%E8%90%BD%E5%85%A5%E9%92%99%E5%8C%96%E6%B1%A0"
    },
    {
      "title": "西安商场坠楼男子好友发声",
      "hot_value": 326875,
      "link": "https://s.weibo.com/weibo?q=%E8%A5%BF%E5%AE%89%E5%95%86%E5%9C%BA%E5%9D%A0%E6%A5%BC%E7%94%B7%E5%AD%90%E5%A5%BD%E5%8F%8B%E5%8F%91%E5%A3%B0"
    },
    {
      "title": "王楚钦孙颖莎vs雨果高桥布鲁娜",
      "hot_value": 326015,
      "link": "https://s.weibo.com/weibo?q=%E7%8E%8B%E6%A5%9A%E9%92%A6%E5%AD%99%E9%A2%96%E8%8E%8Evs%E9%9B%A8%E6%9E%9C%E9%AB%98%E6%A1%A5%E5%B8%83%E9%B2%81%E5%A8%9C"
    },
    {
      "title": "1岁男童失去呼吸奶奶跪地求助",
      "hot_value": 323692,
      "link": "https://s.weibo.com/weibo?q=1%E5%B2%81%E7%94%B7%E7%AB%A5%E5%A4%B1%E5%8E%BB%E5%91%BC%E5%90%B8%E5%A5%B6%E5%A5%B6%E8%B7%AA%E5%9C%B0%E6%B1%82%E5%8A%A9"
    },
    {
      "title": "葡萄牙绝杀克罗地亚",
      "hot_value": 322096,
      "link": "https://s.weibo.com/weibo?q=%E8%91%A1%E8%90%84%E7%89%99%E7%BB%9D%E6%9D%80%E5%85%8B%E7%BD%97%E5%9C%B0%E4%BA%9A"
    },
    {
      "title": "C罗正中要害",
      "hot_value": 319761,
      "link": "https://s.weibo.com/weibo?q=C%E7%BD%97%E6%AD%A3%E4%B8%AD%E8%A6%81%E5%AE%B3"
    },
    {
      "title": "吴世勋分享未公开写真花絮",
      "hot_value": 318671,
      "link": "https://s.weibo.com/weibo?q=%E5%90%B4%E4%B8%96%E5%8B%8B%E5%88%86%E4%BA%AB%E6%9C%AA%E5%85%AC%E5%BC%80%E5%86%99%E7%9C%9F%E8%8A%B1%E7%B5%AE"
    },
    {
      "title": "C罗安慰莫德里奇",
      "hot_value": 317297,
      "link": "https://s.weibo.com/weibo?q=C%E7%BD%97%E5%AE%89%E6%85%B0%E8%8E%AB%E5%BE%B7%E9%87%8C%E5%A5%87"
    },
    {
      "title": "西班牙3比0奥地利",
      "hot_value": 314565,
      "link": "https://s.weibo.com/weibo?q=%E8%A5%BF%E7%8F%AD%E7%89%993%E6%AF%940%E5%A5%A5%E5%9C%B0%E5%88%A9"
    },
    {
      "title": "心疼魔笛",
      "hot_value": 313489,
      "link": "https://s.weibo.com/weibo?q=%E5%BF%83%E7%96%BC%E9%AD%94%E7%AC%9B"
    },
    {
      "title": "蔡文静回应赵一博",
      "hot_value": 311051,
      "link": "https://s.weibo.com/weibo?q=%E8%94%A1%E6%96%87%E9%9D%99%E5%9B%9E%E5%BA%94%E8%B5%B5%E4%B8%80%E5%8D%9A"
    },
    {
      "title": "苹果机密外泄冲击印度制造战略",
      "hot_value": 310116,
      "link": "https://s.weibo.com/weibo?q=%E8%8B%B9%E6%9E%9C%E6%9C%BA%E5%AF%86%E5%A4%96%E6%B3%84%E5%86%B2%E5%87%BB%E5%8D%B0%E5%BA%A6%E5%88%B6%E9%80%A0%E6%88%98%E7%95%A5"
    },
    {
      "title": "阿信相信音乐节阵容",
      "hot_value": 308862,
      "link": "https://s.weibo.com/weibo?q=%E9%98%BF%E4%BF%A1%E7%9B%B8%E4%BF%A1%E9%9F%B3%E4%B9%90%E8%8A%82%E9%98%B5%E5%AE%B9"
    },
    {
      "title": "毛不易 音乐节",
      "hot_value": 306720,
      "link": "https://s.weibo.com/weibo?q=%E6%AF%9B%E4%B8%8D%E6%98%93%20%E9%9F%B3%E4%B9%90%E8%8A%82"
    },
    {
      "title": "王皓逗笑孙颖莎",
      "hot_value": 304959,
      "link": "https://s.weibo.com/weibo?q=%E7%8E%8B%E7%9A%93%E9%80%97%E7%AC%91%E5%AD%99%E9%A2%96%E8%8E%8E"
    },
    {
      "title": "王俊凯新专质量获赞",
      "hot_value": 303513,
      "link": "https://s.weibo.com/weibo?q=%E7%8E%8B%E4%BF%8A%E5%87%AF%E6%96%B0%E4%B8%93%E8%B4%A8%E9%87%8F%E8%8E%B7%E8%B5%9E"
    },
    {
      "title": "王一博人鱼超7万人想看",
      "hot_value": 301876,
      "link": "https://s.weibo.com/weibo?q=%E7%8E%8B%E4%B8%80%E5%8D%9A%E4%BA%BA%E9%B1%BC%E8%B6%857%E4%B8%87%E4%BA%BA%E6%83%B3%E7%9C%8B"
    },
    {
      "title": "女子走路玩手机掉进大锅全身湿透",
      "hot_value": 299014,
      "link": "https://s.weibo.com/weibo?q=%E5%A5%B3%E5%AD%90%E8%B5%B0%E8%B7%AF%E7%8E%A9%E6%89%8B%E6%9C%BA%E6%8E%89%E8%BF%9B%E5%A4%A7%E9%94%85%E5%85%A8%E8%BA%AB%E6%B9%BF%E9%80%8F"
    },
    {
      "title": "孙颖莎说混双更流畅了",
      "hot_value": 298586,
      "link": "https://s.weibo.com/weibo?q=%E5%AD%99%E9%A2%96%E8%8E%8E%E8%AF%B4%E6%B7%B7%E5%8F%8C%E6%9B%B4%E6%B5%81%E7%95%85%E4%BA%86"
    }
  ],
  "code": 200,
  "message": "获取成功。当前部署平台已迁移到 Cloudflare Workers，如有问题请及时反馈。开源地址 https://github.com/vikiboss/60s，反馈群 595941841。"
}